Workbook

Sheet FinalMap
A1: Strategy_Name | B1: ID_Code | C1: Asset_Class | D1: PreMerge_BlendID | E1: MS_SAA_Name | F1: MS_PreMergeEnd_Date | G1: Strategy_Type | H1: Proxied | I1: InvestedID | J1: SAAisComposite | K1: MonitoringEndDate | L1: MonitoringStartDate | M1: MS_SAA_Licensed | N1: ExceptionSAA | O1: Currency | P1: Managed_Account_ID | Q1: Alpha_Target | R1: Tracking_Error
A2: 360 One India | B2: LU2444715366 | C2: Equity | D2: MS_RagSAA1 | E2: MSCI India IMI | F2: 45808 | G2: TF | J2: FALSE | Q2: 0.04 | R2: 0.06
A3: AB Global Healthcare | B3: 719168 | C3: Equity | D3: MS_RagSAA3 | E3: MSCI World/Healthcare | F3: 45808 | G3: Del | O3: EUR | P3: MA503 | Q3: 0.025 | R3: 0.04
A4: Acadian European Equity | B4: 708786 | C4: Equity | D4: MS_RagSAA2 | E4: MSCI Europe | F4: 45808 | G4: Del | O4: EUR | P4: MA105 | Q4: 0.02 | R4: 0.04
A5: Advent Global Balanced Convertible | B5: 724767 | C5: Fixed Income | D5: MS_RagSAA116 | E5: Refinitiv Global Focus Hgd CB TR USD | F5: 45808 | G5: Del | L5: 45991 | O5: USD | P5: MA617 | Q5: 0.02 | R5: 0.03
A6: Algebris Financial Income | B6: 657375 | C6: Fixed Income | D6: MS_RagSAA79 | E6: 15% MSCI World Financial Index local currencies (NDWLFNCL Index) perfectly hedged / 25% The BofA Merrill Lynch Contingent Capital Index EUR hedged (COCO Index) / 60%% ICE BofAML Euro Financial Index (EB00) | F6: 45808 | G6: Del | O6: EUR | P6: MA64 | Q6: 0.02 | R6: 0.045
A7: Alliance Bernstein Sustainable Global Thematic | B7: 719169 | C7: Equity | D7: MS_RagSAA4 | E7: MSCI ACWI | F7: 45808 | G7: Del | K7: 45961 | O7: EUR | P7: MA502 | Q7: 0.015 | R7: 0.06
A8: Allianz Germany | B8: LU0840615578 | C8: Equity | D8: MS_RagSAA5 | E8: MSCI Germany IMI | F8: 45808 | G8: TF | J8: FALSE | K8: 45961 | Q8: 0.025 | R8: 0.05
A9: Alma Eikoh Japan | B9: LU1870374508 | C9: Equity | D9: MS_RagSAA6 | E9: MSCI Japan IMI | F9: 45808 | G9: TF | J9: FALSE | Q9: 0.02 | R9: 0.05
A10: AQR EM Enhanced Equity | B10: 597016 | C10: Equity | D10: MS_RagSAA7 | E10: MSCI EM | F10: 45808 | G10: Del | O10: EUR | P10: MA3 | Q10: 0.01 | R10: 0.03
A11: AQR Global Enhanced Equity | B11: 686585 | C11: Equity | D11: MS_RagSAA8 | E11: MSCI World | F11: 45808 | G11: Del | O11: EUR | P11: MA13 | Q11: 0.01 | R11: 0.03
A12: AQR Pacific Equity | B12: 597012 | C12: Equity | D12: MS_RagSAA9 | E12: MSCI AC Asia Pacific | F12: 45808 | G12: Del | O12: EUR | P12: MA19 | Q12: 0.01 | R12: 0.03
A13: AQR US Enhanced Equity | B13: 597009 | C13: Equity | D13: MS_RagSAA10 | E13: MSCI USA | F13: 45808 | G13: Del | O13: EUR | P13: MA17 | Q13: 0.01 | R13: 0.03
A14: ARGA Global Equity | B14: 724627 | C14: Equity | D14: MS_RagSAA114 | E14: MSCI ACWI Enhanced Value | F14: 45808 | G14: Del | L14: 45960 | O14: EUR | P14: MA610 | Q14: 0.02 | R14: 0.06
A15: Artisan EMD Opportunities | B15: IE0007LWGYY1 | C15: Fixed Income | D15: MS_RagSAA78 | E15: 50% ICE BofA US Emerging Markets External Sovereign / 50% ICE BofA Diversified Emerging Markets Sovereign Bond | F15: 45808 | G15: TF | J15: TRUE | M15: FALSE | O15: EUR | Q15: 0.03 | R15: 0.045
A16: Artisan Global Opportunities | B16: IE00B615T757 | C16: Equity | D16: MS_RagSAA11 | E16: MSCI ACWI Growth | F16: 45808 | G16: TF | J16: FALSE | Q16: 0.015 | R16: 0.06
A17: Artisan Global Value | B17: IE00B4M6YD48 | C17: Equity | D17: MS_RagSAA12 | E17: MSCI ACWI Value | F17: 45808 | G17: TF | J17: FALSE | Q17: 0.025 | R17: 0.05
A18: Atlas Global Infrastructure | B18: IE00BKTZQN06 | C18: Equity | D18: MS_RagSAA13 | E18: 50% FTSE Global Core 50/50 / 50% S&P Global Infrastructure | F18: 45808 | G18: TF | J18: TRUE | M18: FALSE | N18: TRUE | Q18: 0.025 | R18: 0.06
A19: Axiom Concentrated Global Growth | B19: 714548 | C19: Equity | D19: MS_RagSAA14 | E19: MSCI ACWI Growth | F19: 45808 | G19: Del | O19: EUR | P19: MA172 | Q19: 0.02 | R19: 0.07
A20: Axiom Emerging Markets Equity | B20: 716407 | C20: Equity | D20: MS_RagSAA15 | E20: MSCI EM Growth | F20: 45808 | G20: Del | O20: EUR | P20: MA482 | Q20: 0.025 | R20: 0.04
A21: Baillie Gifford Positive Change | B21: 701535 | C21: Equity | D21: MS_RagSAA16 | E21: MSCI ACWI Growth | F21: 45808 | G21: Del | O21: EUR | P21: MA68 | Q21: 0.025 | R21: 0.1
A22: Barings Emerging Markets Sovereign | B22: IE00BM99WQ17 | C22: Fixed Income | D22: MS_RagSAA80 | E22: JPM EMBI Global Diversified | F22: 45808 | G22: TF | J22: FALSE | K22: 45808 | O22: EUR | Q22: 0.022 | R22: #N/A
A23: Bin Yuan All China | B23: LU2200556392 | C23: Equity | D23: MS_RagSAA17 | E23: 50% MSCI China All Shares / 50% MSCI China All Shares Quality | F23: 45808 | G23: TF | J23: TRUE | N23: TRUE | Q23: 0.05 | R23: 0.1
A24: BlackRock Circular Economy | B24: LU2041044764 | C24: Equity | D24: MS_RagSAA18 | E24: MSCI World | F24: 45808 | G24: TF | J24: FALSE | K24: 45869 | Q24: 0.015 | R24: #N/A
A25: BlackRock Continental European Flexible | B25: LU1505937943 | C25: Equity | D25: MS_RagSAA19 | E25: MSCI Europe ex UK Growth | F25: 45808 | G25: TF | J25: FALSE | Q25: 0.025 | R25: 0.055
A26: BlackRock World Energy | B26: 724572 | C26: Equity | D26: MS_RagSAA113 | E26: MSCI World Energy 10/40 | F26: 45808 | G26: Del | O26: EUR | P26: MA613 | Q26: 0.015 | R26: 0.06
A27: BlueBay Global IG Credit | B27: GFJQ | C27: Fixed Income | D27: MS_RagSAA81 | E27: ICE BofA Global Corporate Index (G0BC) | F27: 45808 | G27: Del | O27: EUR | P27: MA124 | Q27: 0.008 | R27: 0.02
A28: BlueBay IG Euro Aggregate | B28: LU0549545142 | C28: Fixed Income | D28: MS_RagSAA82 | E28: Bloomberg Euro Aggregate (EUR) | F28: 45808 | G28: TF | J28: FALSE | M28: FALSE | O28: EUR | Q28: 0.015 | R28: 0.022
A29: BlueBay IG Euro Government | B29: 689939 | C29: Fixed Income | D29: MS_RagSAA83 | E29: BlueBay IG Euro Aggregate Treasury (EUR) | F29: 45808 | G29: Del | O29: EUR | P29: MA6 | Q29: 0.015 | R29: 0.018
A30: BlueBox Global Technology | B30: 722285 | C30: Equity | D30: MS_RagSAA111 | E30: BlueBox Technology - SAA | F30: 45808 | G30: Del | O30: EUR | P30: MA614 | Q30: 0.015 | R30: 0.06
A31: Brigade US High Yield | B31: 692350 | C31: Fixed Income | D31: MS_RagSAA84 | E31: ICE US High Yield (JUC0) - USD | F31: 45808 | G31: Del | O31: USD | P31: MA29 | Q31: 0.01 | R31: 0.03
A32: Capital Four EUR High Yield | B32: GFJY | C32: Fixed Income | D32: MS_RagSAA85 | E32: C4 Composite: ICE European Currency High Yield, then 31/03/2022 65% HPC0 / 34% JUC0 | F32: 45808 | G32: Del | O32: EUR | P32: MA125 | Q32: 0.0075 | R32: 0.02
A33: Deutsche EHY | B33: 681724 | C33: Fixed Income | D33: MS_RagSAA86 | E33: ICE European Currency High Yield Constrained (HPC0, EUR Unhedged) | F33: 45808 | G33: Del | O33: USD | P33: MA36 | Q33: 0.005 | R33: 0.01
A34: DJE GAMAX Junior | B34: 642651 | C34: Equity | D34: MS_RagSAA20 | E34: DJE GAMAX Junior SAA | F34: 45808 | G34: Del | O34: EUR | P34: MA50 | Q34: 0.02 | R34: 0.05
A35: DWS German Equity | B35: 596990 | C35: Equity | D35: MS_RagSAA21 | E35: 85% MSCI Germany / 15% MSCI Germany Small Cap | F35: 45808 | G35: Del | O35: EUR | P35: MA10 | Q35: 0.005 | R35: 0.02
A36: Eagle Capital US Equity Value | B36: 712560 | C36: Equity | D36: MS_RagSAA22 | E36: MSCI USA | F36: 45808 | G36: Del | O36: USD | P36: MA120 | Q36: 0.02 | R36: 0.05
A37: Eleva Euroland | B37: LU1616921232 | C37: Equity | D37: MS_RagSAA23 | E37: MSCI EMU | F37: 45808 | G37: TF | H37: TRUE | I37: LU1920212195 | J37: FALSE | Q37: 0.02 | R37: #N/A
A38: Eleva European Select Equity Large-Cap | B38: 711342 | C38: Equity | D38: MS_RagSAA24 | E38: MSCI Europe Large Cap | F38: 45808 | G38: Del | K38: 45838 | O38: EUR | P38: MA117 | Q38: 0.02 | R38: 0.04
A39: Eleva European Selection | B39: LU1920210579 | C39: Equity | D39: MS_RagSAA25 | E39: MSCI Europe | F39: 45808 | G39: TF | J39: FALSE | Q39: 0.02 | R39: 0.04
A40: Eleva SMID Equity | B40: LU1920216006 | C40: Equity | D40: MS_RagSAA26 | E40: MSCI Europe Small Cap | F40: 45808 | G40: TF | H40: TRUE | I40: LU1920214647 | J40: FALSE | Q40: 0.02 | R40: #N/A
A41: Exane Equity Select Europe | B41: LU1965304444 | C41: Equity | D41: MS_RagSAA27 | E41: MSCI Europe | F41: 45808 | G41: TF | J41: FALSE | Q41: 0.015 | R41: 0.025
A42: Fidelity Germany | B42: LU1968468162 | C42: Equity | D42: MS_RagSAA28 | E42: MSCI Germany IMI | F42: 45808 | G42: TF | J42: FALSE | Q42: 0.015 | R42: 0.04
A43: Fidelity Global Consumer | B43: 707638 | C43: Equity | D43: MS_RagSAA29 | E43: MSCI World Weighted Blend Consumer Discretionary & Consumer Staples (Cap Weighted) - Fidelity | F43: 45808 | G43: Del | K43: 45869 | O43: EUR | P43: MA98 | Q43: 0.02 | R43: #N/A
A44: Fidelity Global Demographics | B44: 714703 | C44: Equity | D44: MS_RagSAA30 | E44: 100% MSCI ACWI till 30/09/2024 then 25% MSCI World Healthcare / 20% MSCI ACWI Growth / 10% MSCI World Small Cap / 40% MSCI Europe / 5% MSCI EM | F44: 45808 | G44: Del | O44: EUR | P44: MA406 | Q44: 0.015 | R44: 0.05
A45: Fidelity Global Industrials/Materials | B45: 718928 | C45: Equity | D45: MS_RagSAA110 | E45: MSCI World Weighted Blend Industrials & Materials | F45: 45808 | G45: Del | O45: EUR | P45: MA499 | Q45: 0.015 | R45: 0.05
A46: First Sentier Global Infrastructure | B46: IE00BFY85J84 | C46: Equity | D46: MS_RagSAA31 | E46: FTSE Global Core 50/50 | F46: 45808 | G46: TF | J46: FALSE | M46: FALSE | N46: TRUE | Q46: 0.02 | R46: 0.06
A47: FountainCap China Opportunity | B47: 716405 | C47: Equity | D47: MS_RagSAA32 | E47: 50% MSCI China All Shares / 50% MSCI China All Shares Quality | F47: 45808 | G47: Del | O47: EUR | P47: MA468 | Q47: 0.05 | R47: 0.08
A48: Franklin Technology | B48: LU0626261944 | C48: Equity | D48: MS_RagSAA33 | E48: MSCI World/Information Technology | F48: 45808 | G48: TF | J48: FALSE | Q48: 0.035 | R48: 0.065
A49: FSSA China Growth | B49: IE00BYXW3909 | C49: Equity | D49: MS_RagSAA115 | E49: MSCI China All Shares | F49: 45808 | G49: TF | J49: FALSE | Q49: 0.04 | R49: 0.08
A50: FvS Bond Opportunities | B50: LU0399027886 | C50: Fixed Income | D50: MS_RagSAA87 | E50: 80% ICE Global Broad Markets EUR Hedged (GBMI) / 20% ICE Global HY Constrained EUR Hedged (HW0C) | F50: 45808 | G50: TF | H50: TRUE | I50: LU2212482017 | J50: TRUE | N50: TRUE | O50: EUR | Q50: 0.018 | R50: #N/A
A51: GS All China Equity | B51: 708787 | C51: Equity | D51: MS_RagSAA34 | E51: MSCI China All Shares | F51: 45808 | G51: Del | O51: EUR | P51: MA109 | Q51: 0.03 | R51: 0.05
A52: GS India | B52: 714113 | C52: Equity | D52: MS_RagSAA35 | E52: MSCI India IMI | F52: 45808 | G52: Del | O52: EUR | P52: MA477 | Q52: 0.04 | R52: 0.06
A53: GuardCap Global Equity | B53: 716542 | C53: Equity | D53: MS_RagSAA36 | E53: 75% MSCI World Quality / 25% MSCI World Low Volatility | F53: 45808 | G53: Del | K53: 45991 | O53: USD | P53: MA484 | Q53: 0.02 | R53: 0.06
A54: Hermes Global Emerging Markets Fund | B54: IE00B3DJ5M15 | C54: Equity | D54: MS_RagSAA37 | E54: MSCI EM | F54: 45808 | G54: TF | J54: FALSE | K54: 46142 | Q54: 0.015 | R54: 0.04
A55: Impax Environmental Leaders | B55: 718556 | C55: Equity | D55: MS_RagSAA38 | E55: MSCI ACWI IMI | F55: 45808 | G55: Del | O55: EUR | P55: MA504 | Q55: 0.015 | R55: 0.05
A56: JPM Europe Dynamic Small Cap | B56: 693765 | C56: Equity | D56: MS_RagSAA39 | E56: MSCI Europe Small Cap | F56: 45808 | G56: Del | K56: 45900 | O56: EUR | P56: MA47 | Q56: 0.02 | R56: #N/A
A57: JPM Pacific Equity | B57: 682593 | C57: Equity | D57: MS_RagSAA40 | E57: MSCI AC Asia Pacific Growth | F57: 45808 | G57: Del | O57: EUR | P57: MA41 | Q57: 0.02 | R57: 0.035
A58: JPM US Aggregate Bond | B58: LU1727358514 | C58: Fixed Income | D58: MS_RagSAA88 | E58: ICE US Broad Market USD Unhedged - (US00) | F58: 45808 | G58: TF | J58: FALSE | O58: USD | Q58: 0.004 | R58: 0.013
A59: JPM US Select | B59: 682592 | C59: Equity | D59: MS_RagSAA41 | E59: MSCI USA | F59: 45808 | G59: Del | O59: EUR | P59: MA43 | Q59: 0.01 | R59: 0.03
A60: Jupiter Dynamic Bond | B60: LU0853555893 | C60: Fixed Income | D60: MS_RagSAA89 | E60: 70% ICE Global Broad Markets EUR Unhedged (GBMI) / 30% Global HY Constrained EUR Unhedged (HW0C) | F60: 45808 | G60: TF | J60: TRUE | K60: 45838 | N60: TRUE | O60: EUR | Q60: 0.008 | R60: #N/A
A61: KBI Circular Economy | B61: 708784 | C61: Equity | D61: MS_RagSAA42 | E61: MSCI ACWI SMID | F61: 45808 | G61: Del | O61: EUR | P61: MA111 | Q61: 0.015 | R61: 0.05
A62: KBI Global Energy Transition | B62: 713420 | C62: Equity | D62: MS_RagSAA43 | E62: WilderHill New Energy Global Innovation | F62: 45808 | G62: Del | O62: EUR | P62: MA150 | Q62: 0.025 | R62: 0.07
A63: Lansdowne European Equity | B63: 716863 | C63: Equity | D63: MS_RagSAA44 | E63: MSCI Europe | F63: 45808 | G63: Del | O63: EUR | P63: MA480 | Q63: 0.02 | R63: 0.05
A64: Lazard Convertible Global | B64: FR0013429446 | C64: Fixed Income | D64: MS_RagSAA98 | E64: Refinitiv Global Focus Hgd CB TR USD | F64: 45808 | G64: TF | J64: FALSE | O64: USD | Q64: 0.01 | R64: #N/A
A65: Lazard Global Convertibles Recovery Fund | B65: IE00BMWVYP76 | C65: Fixed Income | D65: MS_RagSAA99 | E65: Refinitiv Global Focus Hgd CB TR USD | F65: 45808 | G65: TF | J65: FALSE | O65: USD | Q65: 0.02 | R65: 0.05
A66: MAN GLG European High Yield Opportunities | B66: GFJ9 | C66: Fixed Income | D66: MS_RagSAA112 | E66: MAN GLG European High Yield - SAA | F66: 45808 | G66: Del | L66: 45961 | O66: EUR | P66: MA603 | Q66: 0.0125 | R66: 0.035
A67: Manulife India | B67: LU0869500495 | C67: Equity | D67: MS_RagSAA45 | E67: MSCI India IMI | F67: 45808 | G67: TF | J67: FALSE | Q67: 0.02 | R67: 0.04
A68: Mesirow US High Yield | B68: 720798 | C68: Fixed Income | D68: MS_RagSAA105 | E68: 70% ICE US High Yield USD Unhedged (JUC0) / 30% ICE US Small Cap High Yield USD Unhedged (JSML) | F68: 45808 | G68: Del | L68: 45716 | O68: USD | P68: MA515 | Q68: 0.0125 | R68: 0.0325
A69: Metropolis Global Value | B69: 714941 | C69: Equity | D69: MS_RagSAA46 | E69: MSCI ACWI | F69: 45808 | G69: Del | O69: EUR | P69: MA405 | Q69: 0.02 | R69: 0.06
A70: MSIM Global Bond (CH Int Bond) | B70: 689206 | C70: Fixed Income | D70: MS_RagSAA90 | E70: MSIM Global Bond (CH Int Bond) - SAA | F70: 45808 | G70: Del | O70: EUR | P70: MA12 | Q70: 0.005 | R70: 0.0175
A71: MSIM Global Sustainable Bond | B71: 718930 | C71: Fixed Income | D71: MS_RagSAA104 | E71: MSIM Global Sustainable Bond - SAA | F71: 45808 | G71: Del | O71: EUR | P71: MA514 | Q71: 0.012 | R71: 0.026
A72: MSIM Short Duration Global Bond (CH Int Income) | B72: 688330 | C72: Fixed Income | D72: MS_RagSAA102 | E72: MSIM Short Duration Global Bond (CH Int Income) - SAA | F72: 45808 | G72: Del | O72: EUR | P72: MA11 | Q72: 0.005 | R72: 0.0175
A73: Muzinich Dynamic Credit Income | B73: IE00027GCDQ6 | C73: Fixed Income | D73: MS_RagSAA101 | E73: 70% ICE BB-B Global High Yield - HW40 / 30% ICE BBB Global Corporate - GBC4 | F73: 45808 | G73: TF | J73: TRUE | N73: TRUE | O73: USD | Q73: 0.015 | R73: 0.035
A74: Neuberger Berman (Challenge Euro Income) | B74: 689942 | C74: Fixed Income | D74: MS_RagSAA92 | E74: NB Euro Aggregate Treasury 1 - 3 Year (EUR) | F74: 45808 | G74: Del | O74: EUR | P74: MA7 | Q74: 0.005 | R74: 0.015
A75: Neuberger Berman Emerging Market 50/50 Blend (GMB) | B75: GFJW | C75: Fixed Income | D75: MS_RagSAA94 | E75: NB GMB - SAA | F75: 45808 | G75: Del | O75: EUR | P75: MA163 | Q75: 0.015 | R75: 0.035
A76: Neuberger Berman Emerging Market Debt Hard Currency | B76: 693779 | C76: Fixed Income | D76: MS_RagSAA93 | E76: NB EMHC - SAA | F76: 45808 | G76: Del | O76: EUR | P76: MA44 | Q76: 0.015 | R76: 0.038
A77: Ninety One All China Equity | B77: LU1235249262 | C77: Equity | D77: MS_RagSAA47 | E77: MSCI China All Shares | F77: 45808 | G77: TF | J77: FALSE | Q77: 0.02 | R77: #N/A
A78: Ninety One Asia Opportunities | B78: LU1057489228 | C78: Equity | D78: MS_RagSAA48 | E78: MSCI AC Asia Pacific ex Japan | F78: 45808 | G78: TF | J78: FALSE | Q78: 0.0225 | R78: 0.045
A79: NZS Global Technology | B79: 703827 | C79: Equity | D79: MS_RagSAA49 | E79: MSCI World Information Technology & Communication Services Index to Feb 2023. From 02/02/2023 BM changed to 85% MSCI World Information Technology (10/40), 15% MSCI World Media & Entertainmen | F79: 45808 | G79: Del | O79: EUR | P79: MA83 | Q79: 0.03 | R79: 0.05
A80: Oak Hill US High Yield | B80: 722431 | C80: Fixed Income | D80: MS_RagSAA106 | E80: ICE US High Yield (JUC0) - USD | F80: 45808 | G80: Del | O80: USD | P80: MA519 | Q80: 0.01 | R80: 0.025
A81: ODDO Europe Avenir | B81: FR0000974149 | C81: Equity | D81: MS_RagSAA50 | E81: MSCI Europe SMID Growth | F81: 45808 | G81: TF | H81: TRUE | I81: FR0014000DI1 | J81: FALSE | K81: 45808 | Q81: 0.015 | R81: #N/A
A82: PGIM Emerging Market Blend | B82: GFJX | C82: Fixed Income | D82: MS_RagSAA96 | E82: PGIM EM Blend - SAA | F82: 45808 | G82: Del | O82: EUR | P82: MA134 | Q82: 0.011 | R82: 0.03
A83: PGIM Emerging Market Debt Corporates | B83: 666297 | C83: Fixed Income | D83: MS_RagSAA95 | E83: PGIM EM Corporate - SAA | F83: 45808 | G83: Del | O83: USD | P83: MA38 | Q83: 0.01 | R83: 0.03
A84: PGIM Emerging Market Hard Currency Debt Fund | B84: IE00BZCG7W10 | C84: Fixed Income | D84: MS_RagSAA103 | E84: JPM EMBI Global Diversified (USD) | F84: 45808 | G84: TF | J84: FALSE | M84: FALSE | O84: USD | Q84: 0.012 | R84: 0.03
A85: PGIM Emerging Market Local Currency | B85: 716679 | C85: Fixed Income | D85: MS_RagSAA97 | E85: Splice JPM GBI-EM Global Diversified / ICE Diversified Emerging Markets Sovereign Bond (USD) | F85: 45808 | G85: Del | O85: USD | P85: MA490 | Q85: 0.01 | R85: 0.03
A86: Pictet Circular Economy | B86: 708783 | C86: Equity | D86: MS_RagSAA51 | E86: MSCI ACWI Growth | F86: 45808 | G86: Del | O86: EUR | P86: MA112 | Q86: 0.015 | R86: 0.05
A87: Pictet Clean Energy | B87: 713421 | C87: Equity | D87: MS_RagSAA52 | E87: MSCI ACWI SMID | F87: 45808 | G87: Del | O87: EUR | P87: MA151 | Q87: 0.03 | R87: 0.09
A88: Pictet Nutrition | B88: 713971 | C88: Equity | D88: MS_RagSAA53 | E88: 35% MSCI World Consumer Staples / 20% MSCI World Materials / 20% MSCI World Small Cap / 15% MSCI World Industrials / 10% MSCI World Healthcare | F88: 45808 | G88: Del | K88: 46142 | O88: EUR | P88: MA474 | Q88: 0.01 | R88: 0.045
A89: PineStone Global Equity | B89: 716844 | C89: Equity | D89: MS_RagSAA54 | E89: MSCI ACWI Quality | F89: 45808 | G89: Del | O89: EUR | P89: MA483 | Q89: 0.02 | R89: 0.06
A90: Pzena Global Value | B90: 706632 | C90: Equity | D90: MS_RagSAA55 | E90: MSCI World Enhanced Value | F90: 45808 | G90: Del | O90: EUR | P90: MA97 | Q90: 0.02 | R90: 0.06
A91: Quoniam Pan European | B91: 714291 | C91: Equity | D91: MS_RagSAA56 | E91: MSCI Europe Small Cap | F91: 45808 | G91: Del | K91: 45900 | O91: EUR | P91: MA167 | Q91: 0.015 | R91: #N/A
A92: Robeco Asia Pacific Equity | B92: LU1493701376 | C92: Equity | D92: MS_RagSAA57 | E92: MSCI AC Asia Pacific Value | F92: 45808 | G92: TF | J92: FALSE | Q92: 0.025 | R92: 0.04
A93: Robeco Emerging Market Equities | B93: 684489 | C93: Equity | D93: MS_RagSAA58 | E93: MSCI EM | F93: 45808 | G93: Del | O93: EUR | P93: MA4 | Q93: 0.02 | R93: 0.04
A94: Robeco Green Buildings | B94: 718931 | C94: Equity | D94: MS_RagSAA108 | E94: Robeco Green Buildings - SAA | F94: 45808 | G94: Del | O94: EUR | P94: MA510 | Q94: 0.015 | R94: 0.05
A95: Robeco Sustainable Global Stars | B95: 682590 | C95: Equity | D95: MS_RagSAA59 | E95: MSCI World | F95: 45808 | G95: Del | O95: EUR | P95: MA42 | Q95: 0.02 | R95: 0.035
A96: RWC Emerging Markets | B96: LU1802245560 | C96: Equity | D96: MS_RagSAA60 | E96: 50% MSCI EM IMI / 50% MSCI EM IMI Growth | F96: 45808 | G96: TF | J96: TRUE | N96: TRUE | Q96: 0.035 | R96: 0.08
A97: Sanders Capital Global Value | B97: 716958 | C97: Equity | D97: MS_RagSAA61 | E97: MSCI ACWI Value | F97: 45808 | G97: Del | O97: EUR | P97: MA486 | Q97: 0.02 | R97: 0.05
A98: Sands Capital Emerging Markets Growth | B98: IE00BF21WN20 | C98: Equity | D98: MS_RagSAA62 | E98: MSCI EM Growth | F98: 45808 | G98: TF | J98: FALSE | Q98: 0.03 | R98: 0.075
A99: Sands Capital Global Growth | B99: 716406 | C99: Equity | D99: MS_RagSAA63 | E99: MSCI ACWI Growth | F99: 45808 | G99: Del | O99: EUR | P99: MA467 | Q99: 0.015 | R99: 0.07
A100: Schroders China Opportunities | B100: 693764 | C100: Equity | D100: MS_RagSAA64 | E100: MSCI China All Shares | F100: 45808 | G100: Del | O100: EUR | P100: MA46 | Q100: 0.035 | R100: 0.06
...

Sheet TE_AT_112025
A1: DelCodeISIN | B1: Strategy Name | C1: Asset Manager | D1: Analyst Estimate - Excess Return | E1: Analyst Estimate - Tracking Error
A2: 169963 | B2: Sector Gamma Health Care | C2: Sector Gamma | D2: 2.5 | E2: 5
A3: 170032 | B3: Arga Global Value | C3: Arga | D3: 2 | E3: 6
A4: 170730 | B4: Impax Environmental Leaders | C4: Impax | D4: 1.5 | E4: 5
A5: 170733 | B5: Impax Nutrition | C5: Impax | D5: 1.5 | E5: 5
A6: 596990 | B6: DWS German Equity | C6: DWS | D6: 0.5 | E6: 2
A7: 596994 | B7: Trea Spain Equity | C7: Trea | D7: 0 | E7: 2
A8: 596998 | B8: Wellington Global Research Equity | C8: Wellington | D8: 1 | E8: 3
A9: 597009 | B9: AQR North America Equity | C9: AQR | D9: 1 | E9: 3
A10: 597012 | B10: AQR Pacific Equity | C10: AQR | D10: 1 | E10: 3
A11: 597016 | B11: AQR Emerging Markets Equity | C11: AQR | D11: 1 | E11: 3
A12: 642651 | B12: DJE Gamax Junior | C12: DJE | D12: 2 | E12: 5
A13: 645766 | B13: Tenax Financial Equity | C13: Tenax | D13: 1.5 | E13: 4.5
... A116: 729695 | B116: KAR International Small Cap Quality | C116: Kayne Anderson Rudnick | D116: 3 | E116: 7
A117: GFJ8 | B117: Muzinich Euro High Yield | C117: Muzinich | D117: 0.8 | E117: 2
A118: GFJ9 | B118: Man GLG European High Yield Opportunities | C118: Man Group | D118: 1.25 | E118: 3.5
A119: GFJQ | B119: BlueBay Global IG Credit (GMB) | C119: BlueBay | D119: 0.8 | E119: 2
A120: GFJR | B120: Deutsche Invest European High Yield | C120: DWS | D120: 0.5 | E120: 1
A121: GFJS | B121: Deutsche Invest European High Yield | C121: DWS | D121: 0.5 | E121: 1
A122: GFJU | B122: Brigade High Yield (GMB) | C122: Brigade | D122: 1 | E122: 3
A123: GFJW | B123: Neuberger Berman Emerging Market 50/50 Blend (GMB) | C123: Neuberger Berman | D123: 1.5 | E123: 3.5
A124: GFJX | B124: PGIM Emerging Market Blend (GMB) | C124: PGIM | D124: 1.1 | E124: 3
A125: GFJY | B125: Capital Four EUR High Yield | C125: Capital Four | D125: 0.75 | E125: 2
A126: Robeco1_6124 | B126: Robeco Global Equity (Compromiso) | C126: Robeco | D126: 0.5 | E126: 3
A127: IE0000AQF1T2 | B127: Acadian Europe | C127: Acadian | D127: 2 | E127: 4
A128: IE0000AQF1T2 | B128: Acadian Europe | C128: Acadian | D128: 2 | E128: 4
... A215: LU2990521093 | B215: Mirabaud Sustainable Convertibles Global | C215: Mirabaud | D215: 1.2 | E215: 4

Sheet Sheet3
A1: TARGET_FUND_ID | B1: TARGET_FUND_INSTRUMENT_ID | C1: MANAGER_ORGANISATION_ID | D1: TARGET_FUND_NAME | E1: ISIN_INSTRUMENT_REFERENCE | F1: BLOOMBERG_INSTRUMENT_REFERENCE | G1: HEDGED_INDICATOR | H1: CURRENCY_ID | I1: CREATED_DATETIME | J1: UPDATED_DATETIME | K1: CREATED_BY_USER | L1: UPDATED_BY_USER
A2: 6 | B2: 5356 | C2: 4 | D2: BGF-CONT EUR FLX-I4 EUR | E2: LU1505937943 | F2: BBG00F0FKNN4 | G2: N | H2: 1 | I2: 45853.502 | J2: 45853.502 | K2: Unknown | L2: Unknown
A3: 8 | B3: 5626 | C3: 34 | D3: BLUEBAY INV GR EU AG B-Q EUR | E3: LU1170327289 | F3: BBG00CGLS776 | G3: N | H3: 1 | I3: 45853.502 | J3: 45853.502 | K3: Unknown | L3: Unknown
A4: 9 | B4: 3188 | C4: 0 | D4: ALLIANZ THEMATICA-WT EUR A | E4: LU2106854214 | F4: BBG00RKBXW06 | G4: N | H4: 1 | I4: 45853.502 | J4: 45853.502 | K4: Unknown | L4: Unknown
A5: 10 | B5: 7014 | C5: 26 | D5: MRG ST IF-SH MAT EU BD-ZE | E5: LU0360478795 | F5: BBG000C4LYZ1 | G5: N | H5: 1 | I5: 45853.502 | J5: 45853.502 | K5: Unknown | L5: Unknown
A6: 12 | B6: 2011 | C6: 0 | D6: MU-GL TAC CR-H EUR ACC G2 UN | E6: IE00BKSKL532 | F6: BBG00RMFXX49 | G6: N | H6: 1 | I6: 45853.502 | J6: 45853.502 | K6: Unknown | L6: Unknown
A7: 15 | B7: 6762 | C7: 94 | D7: DWS- INVEST- EU H YL CP-RDQ | E7: LU1808738642 | F7: BBG00L4K30S0 | G7: N | H7: 1 | I7: 45853.502 | J7: 45853.502 | K7: Unknown | L7: Unknown
A8: 17 | B8: 6882 | C8: 111 | D8: AB SICAV I-INTL HLT CR-S1EPC | E8: LU0260062871 | F8: BBG00PZZQKQ7 | G8: N | H8: 1 | I8: 45853.502 | J8: 45853.502 | K8: Unknown | L8: Unknown
A9: 18 | B9: 5938 | C9: 26 | D9: MSIF-GLOBAL OPPORT-ZH1 EUR | E9: LU2646745732 | F9: BBG01HCV83F8 | G9: N | H9: 1 | I9: 45853.502 | J9: 45853.502 | K9: Unknown | L9: Unknown
A10: 19 | B10: 4992 | C10: 50 | D10: JUPITER JGF DY B FD-I EUR A | E10: LU0853555893 | F10: BBG003NXFNJ8 | G10: N | H10: 1 | I10: 45853.502 | J10: 45853.502 | K10: Unknown | L10: Unknown
A11: 20 | B11: 3571 | C11: 24 | D11: PGIM E/M HRD CUR DB-IDIS | E11: IE000VNQZC87 | F11: BBG013V235H0 | G11: N | H11: 1 | I11: 45853.502 | J11: 45853.502 | K11: Unknown | L11: Unknown
A12: 21 | B12: 1625 | C12: 34 | D12: BLUEBAY INV GR EUR AGG BD-I | E12: LU0549545142 | F12: BBG0018YWBM0 | G12: N | H12: 1 | I12: 45853.502 | J12: 45853.502 | K12: Unknown | L12: Unknown
A13: 23 | B13: 6196 | C13: 36 | D13: CARMIGNAC EMERGENTS-A EUR AC | E13: FR0010149302 | F13: BBG000C0P7T1 | G13: N | H13: 1 | I13: 45853.502 | J13: 45853.502 | K13: Unknown | L13: Unknown
... A165: 164 | B165: 15070695 | C165: 39 | D165: SCHR ISF-GBL SST VAL-IZUSDAC | E165: LU2405386017 | F165: EQ0000000090199151 | G165: N | H165: 153 | I165: 45853.502 | J165: 45853.502 | K165: Unknown | L165: Unknown

Sheet IAvMS_MAP
A1: ID_Code | B1: SophisID | C1: Name | D1: DBCode | E1: FundName | F1: AssetClass | G1: Region | H1: Style | I1: StartDate | J1: EndDate | K1: IsRepresentative | L1: BaseCCY | M1: MsMap | N1: MsStratName | O1: IsUsedforMsRAG | P1: Type | Q1: MappedToType | R1: Note
A2: 708786 | B2: 2422 | C2: Acadian | D2: DB8813 | E2: CH EUROPEAN EQUITY | F2: Equity | G2: Europe | H2: Blend | I2: 44508 | J2: NULL | K2: 1 | L2: EUR | M2: 708786 | N2: Acadian European Equity | O2: TRUE | P2: =IF(LEN(A2)>8,"TF","Del") -> Del | Q2: =IF(LEN(M2)>8,"TF","Del") -> Del
A3: 724767 | B3: 4121 | C3: Advent | D3: DB2016 | E3: MBB CONVERTIBLE STRATEGY COLLECTION | F3: Hybrid | G3: Global | H3: Blend | I3: 45630 | J3: NULL | K3: 1 | L3: USD | M3: 724767 | N3: Advent Global Balanced Convertible | O3: TRUE | P3: =IF(LEN(A3)>8,"TF","Del") -> Del | Q3: =IF(LEN(M3)>8,"TF","Del") -> Del
A4: 657375 | B4: 922 | C4: Algebris | D4: DB6214 | E4: MBB FINANCIAL INCOME STRATEGY | F4: MultiAsset | G4: Global | H4: Income | I4: 42086 | J4: NULL | K4: 1 | L4: EUR | M4: 657375 | N4: Algebris Financial Income | O4: TRUE | P4: =IF(LEN(A4)>8,"TF","Del") -> Del | Q4: =IF(LEN(M4)>8,"TF","Del") -> Del
A5: 719168 | B5: 3782 | C5: AllianceBernstein | D5: DB3784 | E5: CH HEALTHCARE EQUITY EVO. | F5: Equity | G5: Global | H5: Sec_Healthcare | I5: 45257 | J5: NULL | K5: 1 | L5: EUR | M5: 719168 | N5: AB Global Healthcare | O5: TRUE | P5: =IF(LEN(A5)>8,"TF","Del") -> Del | Q5: =IF(LEN(M5)>8,"TF","Del") -> Del
A6: 719169 | B6: 3781 | C6: AllianceBernstein | D6: DB6459 | E6: MBB INNOVATIVE THEMATIC OPPORTUNITIES | F6: Equity | G6: Global | H6: Quality | I6: 45257 | J6: NULL | K6: 1 | L6: EUR | M6: 719169 | N6: Alliance Bernstein Sustainable Global Thematic | O6: TRUE | P6: =IF(LEN(A6)>8,"TF","Del") -> Del | Q6: =IF(LEN(M6)>8,"TF","Del") -> Del
A7: 597012 | B7: 1261 | C7: AQR | D7: DB8814 | E7: CH PACIFIC EQUITY | F7: Equity | G7: APAC | H7: Value | I7: 43297 | J7: NULL | K7: 1 | L7: EUR | M7: 597012 | N7: AQR Pacific Equity | O7: TRUE | P7: =IF(LEN(A7)>8,"TF","Del") -> Del | Q7: =IF(LEN(M7)>8,"TF","Del") -> Del
A8: 597016 | B8: 1201 | C8: AQR | D8: DB8816 | E8: CH EMERGING MARKETS EQUITY | F8: Equity | G8: EM | H8: Value | I8: 43283 | J8: NULL | K8: 1 | L8: EUR | M8: 597016 | N8: AQR EM Enhanced Equity | O8: TRUE | P8: =IF(LEN(A8)>8,"TF","Del") -> Del | Q8: =IF(LEN(M8)>8,"TF","Del") -> Del
A9: 707793 | B9: 2381 | C9: AQR | D9: DB8824 | E9: CH PROVIDENT 1 | F9: Equity | G9: Global | H9: Value | I9: 44424 | J9: NULL | K9: 1 | L9: EUR | M9: 686585 | N9: AQR Global Enhanced Equity | O9: FALSE | P9: =IF(LEN(A9)>8,"TF","Del") -> Del | Q9: =IF(LEN(M9)>8,"TF","Del") -> Del
A10: 727783 | B10: 4281 | C10: AQR | D10: DB5555 | E10: MBB SOCIALLY RESPONSIBLE COLLECTION | F10: Equity | G10: Global | H10: Blend | I10: 45775 | J10: NULL | K10: 0 | L10: EUR | M10: 686585 | N10: AQR Global Enhanced Equity | O10: FALSE | P10: =IF(LEN(A10)>8,"TF","Del") -> Del | Q10: =IF(LEN(M10)>8,"TF","Del") -> Del
A11: 686585 | B11: 1202 | C11: AQR | D11: DB4223 | E11: CH INTERNATIONAL EQUITY | F11: Equity | G11: Global | H11: Blend | I11: 43283 | J11: NULL | K11: 1 | L11: EUR | M11: 686585 | N11: AQR Global Enhanced Equity | O11: TRUE | P11: =IF(LEN(A11)>8,"TF","Del") -> Del | Q11: =IF(LEN(M11)>8,"TF","Del") -> Del
A12: 597009 | B12: 1203 | C12: AQR | D12: DB8812 | E12: CH NORTH AMERICAN EQUITY | F12: Equity | G12: US | H12: Value | I12: 43283 | J12: NULL | K12: 1 | L12: EUR | M12: 597009 | N12: AQR US Enhanced Equity | O12: TRUE | P12: =IF(LEN(A12)>8,"TF","Del") -> Del | Q12: =IF(LEN(M12)>8,"TF","Del") -> Del
A13: 727790 | B13: 4261 | C13: Arga | D13: DB4211 | E13: MBB EQUITY POWER COUPON COLLECTION | F13: Equity | G13: Global | H13: Value | I13: 45770 | J13: NULL | K13: 1 | L13: EUR | M13: 724627 | N13: ARGA Global Equity | O13: FALSE | P13: =IF(LEN(A13)>8,"TF","Del") -> Del | Q13: =IF(LEN(M13)>8,"TF","Del") -> Del
... A26: 689939 | B26: 1365 | C26: Bluebay | D26: DB8818 | E26: CH EURO BOND | F26: FixedIncome | G26: Europe | H26: Government | I26: 43410 | J26: NULL | K26: 1 | L26: EUR | M26: 689939 | N26: BlueBay IG Euro Government | O26: TRUE | P26: =IF(LEN(A26)>8,"TF","Del") -> Del | Q26: =IF(LEN(M26)>8,"TF","Del") -> Del
A27: GFJQ | B27: 2566 | C27: Bluebay | D27: CHIN | E27: MGF GLOBALE MULTI BOND | F27: FixedIncome | G27: Global | H27: Aggregate | I27: 44599 | J27: NULL | K27: 1 | L27: EUR | M27: GFJQ | N27: BlueBay Global IG Credit | O27: TRUE | P27: =IF(LEN(A27)>8,"TF","Del") -> Del | Q27: =IF(LEN(M27)>8,"TF","Del") -> Del
A28: 722285 | B28: 4101 | C28: BlueBox | D28: DB3785 | E28: CH TECHNOLOGY EQUITY EVO. | F28: Equity | G28: Global | H28: Sec_Tech | I28: 45618 | J28: NULL | K28: 1 | L28: EUR | M28: 722285 | N28: BlueBox Global Technology | O28: TRUE | P28: =IF(LEN(A28)>8,"TF","Del") -> Del | Q28: =IF(LEN(M28)>8,"TF","Del") -> Del
A29: GFJU | B29: 2570 | C29: Brigade | D29: CHIN | E29: MGF GLOBALE MULTI BOND | F29: FixedIncome | G29: US | H29: HighYield | I29: 44599 | J29: NULL | K29: 0 | L29: EUR | M29: 692350 | N29: Brigade US High Yield | O29: FALSE | P29: =IF(LEN(A29)>8,"TF","Del") -> Del | Q29: =IF(LEN(M29)>8,"TF","Del") -> Del
A30: 692350 | B30: 1441 | C30: Brigade | D30: DB3015 | E30: MBB GLOBAL HIGH YIELD | F30: FixedIncome | G30: US | H30: HighYield | I30: 43586 | J30: NULL | K30: 1 | L30: USD | M30: 692350 | N30: Brigade US High Yield | O30: TRUE | P30: =IF(LEN(A30)>8,"TF","Del") -> Del | Q30: =IF(LEN(M30)>8,"TF","Del") -> Del
A31: GFJY | B31: 2572 | C31: Capital Four | D31: CREA | E31: MGF EURO HIGH YIELD | F31: FixedIncome | G31: Europe | H31: HighYield | I31: 44599 | J31: NULL | K31: 1 | L31: EUR | M31: GFJY | N31: Capital Four EUR High Yield | O31: TRUE | P31: =IF(LEN(A31)>8,"TF","Del") -> Del | Q31: =IF(LEN(M31)>8,"TF","Del") -> Del
A32: 642651 | B32: 961 | C32: DJE | D32: LU4136 | E32: GAMAX FUNDS JUNIOR | F32: Equity | G32: Global | H32: Sec_Consumer | I32: 41302 | J32: NULL | K32: 1 | L32: EUR | M32: 642651 | N32: DJE GAMAX Junior | O32: TRUE | P32: =IF(LEN(A32)>8,"TF","Del") -> Del | Q32: =IF(LEN(M32)>8,"TF","Del") -> Del
A33: 596990 | B33: 1062 | C33: DWS | D33: DB3896 | E33: CH GERMANY EQUITY | F33: Equity | G33: Germany | H33: Blend | I33: 42919 | J33: NULL | K33: 1 | L33: EUR | M33: 596990 | N33: DWS German Equity | O33: TRUE | P33: =IF(LEN(A33)>8,"TF","Del") -> Del | Q33: =IF(LEN(M33)>8,"TF","Del") -> Del
A34: GFJR | B34: 2565 | C34: DWS | D34: CHIN | E34: MGF GLOBALE MULTI BOND | F34: FixedIncome | G34: Europe | H34: HighYield | I34: 44599 | J34: NULL | K34: 0 | L34: EUR | M34: 681724 | N34: Deutsche EHY | O34: FALSE | P34: =IF(LEN(A34)>8,"TF","Del") -> Del | Q34: =IF(LEN(M34)>8,"TF","Del") -> Del
A35: GFJS | B35: 2574 | C35: DWS | D35: CREA | E35: MGF EURO HIGH YIELD | F35: FixedIncome | G35: Europe | H35: HighYield | I35: 44599 | J35: NULL | K35: 0 | L35: EUR | M35: 681724 | N35: Deutsche EHY | O35: FALSE | P35: =IF(LEN(A35)>8,"TF","Del") -> Del | Q35: =IF(LEN(M35)>8,"TF","Del") -> Del
A36: 681724 | B36: 1101 | C36: DWS | D36: DB3015 | E36: MBB GLOBAL HIGH YIELD | F36: FixedIncome | G36: Europe | H36: HighYield | I36: 43061 | J36: NULL | K36: 1 | L36: EUR | M36: 681724 | N36: Deutsche EHY | O36: TRUE | P36: =IF(LEN(A36)>8,"TF","Del") -> Del | Q36: =IF(LEN(M36)>8,"TF","Del") -> Del
A37: 712560 | B37: 2741 | C37: Eagle | D37: DB8812 | E37: CH NORTH AMERICAN EQUITY | F37: Equity | G37: US | H37: Blend | I37: 44706 | J37: NULL | K37: 1 | L37: USD | M37: 712560 | N37: Eagle Capital US Equity Value | O37: TRUE | P37: =IF(LEN(A37)>8,"TF","Del") -> Del | Q37: =IF(LEN(M37)>8,"TF","Del") -> Del
A38: 711342 | B38: 2681 | C38: Eleva | D38: DB8813 | E38: CH EUROPEAN EQUITY | F38: Equity | G38: Europe | H38: Blend | I38: 44691 | J38: NULL | K38: 1 | L38: EUR | M38: 711342 | N38: Eleva European Select Equity Large-Cap | O38: TRUE | P38: =IF(LEN(A38)>8,"TF","Del") -> Del | Q38: =IF(LEN(M38)>8,"TF","Del") -> Del
A39: 729235 | B39: 4381 | C39: Evolutionary Tree | D39: DB6459 | E39: MBB INNOVATIVE THEMATIC OPPORTUNITIES | F39: Equity | G39: Global | H39: Growth | I39: 45813 | J39: NULL | K39: 1 | L39: EUR | O39: FALSE | P39: =IF(LEN(A39)>8,"TF","Del") -> Del | Q39: =IF(LEN(M39)>8,"TF","Del") -> Del
A40: 718928 | B40: 3741 | C40: Fidelity | D40: DB3789 | E40: CH INDUSTRIALS AND MATERIALS EQUITY EVO. | F40: Equity | G40: Global | H40: Sec_IndMat | I40: 45240 | J40: NULL | K40: 1 | L40: EUR | M40: 718928 | N40: Fidelity Global Industrials/Materials | O40: TRUE | P40: =IF(LEN(A40)>8,"TF","Del") -> Del | Q40: =IF(LEN(M40)>8,"TF","Del") -> Del
A41: 714703 | B41: 3102 | C41: Fidelity | D41: DB6484 | E41: MBB GLOBAL DEMOGRAPHIC OPPORTUNITIES | F41: Equity | G41: Global | H41: Quality | I41: 44897 | J41: NULL | K41: 1 | L41: EUR | M41: 714703 | N41: Fidelity Global Demographics | O41: TRUE | P41: =IF(LEN(A41)>8,"TF","Del") -> Del | Q41: =IF(LEN(M41)>8,"TF","Del") -> Del
A42: 707638 | B42: 2321 | C42: Fidelity | D42: LU4136 | E42: GAMAX FUNDS JUNIOR | F42: Equity | G42: Sec_Consumer | H42: Quality | I42: 44403 | J42: NULL | K42: 1 | L42: EUR | M42: 707638 | N42: Fidelity Global Consumer | O42: TRUE | P42: =IF(LEN(A42)>8,"TF","Del") -> Del | Q42: =IF(LEN(M42)>8,"TF","Del") -> Del
A43: 722394 | B43: 3922 | C43: FirstSentier | D43: DB6510 | E43: MBB GLOBAL IMPACT | F43: Equity | G43: Global | H43: Quality | I43: 45456 | J43: NULL | K43: 1 | L43: EUR | M43: 722394 | N43: Stewart Worldwide Sustainability | O43: TRUE | P43: =IF(LEN(A43)>8,"TF","Del") -> Del | Q43: =IF(LEN(M43)>8,"TF","Del") -> Del
A44: 716405 | B44: 3341 | C44: FountainCap | D44: DB6501 | E44: MBB CHINESE ROAD OPPORTUNITIES | F44: Equity | G44: China | H44: Quality | I44: 45037 | J44: NULL | K44: 1 | L44: EUR | M44: 716405 | N44: FountainCap China Opportunity | O44: TRUE | P44: =IF(LEN(A44)>8,"TF","Del") -> Del | Q44: =IF(LEN(M44)>8,"TF","Del") -> Del
A45: 708787 | B45: 2501 | C45: Goldman Sachs | D45: DB6501 | E45: MBB CHINESE ROAD OPPORTUNITIES | F45: Equity | G45: China | H45: Blend | I45: 44533 | J45: NULL | K45: 1 | L45: EUR | M45: 708787 | N45: GS All China Equity | O45: TRUE | P45: =IF(LEN(A45)>8,"TF","Del") -> Del | Q45: =IF(LEN(M45)>8,"TF","Del") -> Del
A46: 714113 | B46: 3022 | C46: Goldman Sachs | D46: DB6575 | E46: MBB INDIA OPPORTUNITIES | F46: Equity | G46: EM | H46: Blend | I46: 45065 | J46: NULL | K46: 1 | L46: EUR | M46: 714113 | N46: GS India | O46: TRUE | P46: =IF(LEN(A46)>8,"TF","Del") -> Del | Q46: =IF(LEN(M46)>8,"TF","Del") -> Del
A47: 716542 | B47: 3461 | C47: GuardCap | D47: DB6592 | E47: MBB GLOBAL EQUITY STYLE SELECTION | F47: Equity | G47: Global | H47: Quality | I47: 45065 | J47: NULL | K47: 1 | L47: USD | M47: 716542 | N47: GuardCap Global Equity | O47: TRUE | P47: =IF(LEN(A47)>8,"TF","Del") -> Del | Q47: =IF(LEN(M47)>8,"TF","Del") -> Del
A48: 716541 | B48: 3501 | C48: GuardCap | D48: DB6502 | E48: MBB GLOBAL LEADERS | F48: Equity | G48: Global | H48: Quality | I48: 45072 | J48: NULL | K48: 0 | L48: USD | M48: 716542 | N48: GuardCap Global Equity | O48: FALSE | P48: =IF(LEN(A48)>8,"TF","Del") -> Del | Q48: =IF(LEN(M48)>8,"TF","Del") -> Del
A49: 718556 | B49: 3721 | C49: Impax | D49: DB6510 | E49: MBB GLOBAL IMPACT | F49: Equity | G49: Global | H49: Blend | I49: 45233 | J49: NULL | K49: 1 | L49: EUR | M49: 718556 | N49: Impax Environmental Leaders | O49: TRUE | P49: =IF(LEN(A49)>8,"TF","Del") -> Del | Q49: =IF(LEN(M49)>8,"TF","Del") -> Del
A50: 716676 | B50: 3621 | C50: JPMorgan | D50: LU4133 | E50: GAMAX FUNDS ASIA PACIFIC | F50: Equity | G50: APAC | H50: Growth | I50: 45191 | J50: NULL | K50: 0 | L50: EUR | M50: 682593 | N50: JPM Pacific Equity | O50: FALSE | P50: =IF(LEN(A50)>8,"TF","Del") -> Del | Q50: =IF(LEN(M50)>8,"TF","Del") -> Del
A51: 682593 | B51: 1127 | C51: JPMorgan | D51: DB3017 | E51: MBB PACIFIC COLLECTION | F51: Equity | G51: APAC | H51: Growth | I51: 43088 | J51: NULL | K51: 1 | L51: EUR | M51: 682593 | N51: JPM Pacific Equity | O51: TRUE | P51: =IF(LEN(A51)>8,"TF","Del") -> Del | Q51: =IF(LEN(M51)>8,"TF","Del") -> Del
... A60: 717479 | B60: 3561 | C60: Lansdowne | D60: DB3018 | E60: MBB EUROPEAN COLLECTION | F60: Equity | G60: Europe | H60: Blend | I60: 45107 | J60: NULL | K60: 0 | L60: EUR | M60: 716863 | N60: Lansdowne European Equity | O60: FALSE | P60: =IF(LEN(A60)>8,"TF","Del") -> Del | Q60: =IF(LEN(M60)>8,"TF","Del") -> Del
A61: 727794 | B61: 4321 | C61: Lazard | D61: DB6622 | E61: MBB WORLD INNOVATIVE LEADERS | F61: Equity | G61: Global | H61: Core | I61: 45785 | J61: NULL | K61: 1 | L61: EUR | O61: FALSE | P61: =IF(LEN(A61)>8,"TF","Del") -> Del | Q61: =IF(LEN(M61)>8,"TF","Del") -> Del
A62: GFJ9 | B62: 3961 | C62: MAN | D62: CREA | E62: MGF EURO HIGH YIELD | F62: FixedIncome | G62: Europe | H62: HighYield | I62: 45537 | J62: NULL | K62: 1 | L62: EUR | M62: GFJ9 | N62: MAN GLG European High Yield Opportunities | O62: TRUE | P62: =IF(LEN(A62)>8,"TF","Del") -> Del | Q62: =IF(LEN(M62)>8,"TF","Del") -> Del
A63: 720798 | B63: 3821 | C63: Mesirow | D63: DB3015 | E63: MBB GLOBAL HIGH YIELD | F63: FixedIncome | G63: US | H63: HighYield | I63: 45355 | J63: NULL | K63: 1 | L63: USD | M63: 720798 | N63: Mesirow US High Yield | O63: TRUE | P63: =IF(LEN(A63)>8,"TF","Del") -> Del | Q63: =IF(LEN(M63)>8,"TF","Del") -> Del
A64: 714941 | B64: 3101 | C64: Metropolis | D64: DB6342 | E64: MBB DYNAMIC INTERNATIONAL VALUE OPPORTUNITIES | F64: Equity | G64: Global | H64: Value | I64: 44904 | J64: NULL | K64: 1 | L64: EUR | M64: 714941 | N64: Metropolis Global Value | O64: TRUE | P64: =IF(LEN(A64)>8,"TF","Del") -> Del | Q64: =IF(LEN(M64)>8,"TF","Del") -> Del
A65: 682588 | B65: 1122 | C65: Morgan Stanley | D65: DB2015 | E65: MBB INFRASTRUCTURE OPPORTUNITIES COLLECTION | F65: Equity | G65: Global | H65: Blend | I65: 43082 | J65: NULL | K65: 1 | L65: EUR | M65: 682588 | N65: Morgan Stanley Global Infrastr | O65: TRUE | P65: =IF(LEN(A65)>8,"TF","Del") -> Del | Q65: =IF(LEN(M65)>8,"TF","Del") -> Del
A66: 688330 | B66: 1301 | C66: Morgan Stanley | D66: DB5199 | E66: CH INTERNATIONAL INCOME | F66: FixedIncome | G66: Global | H66: ShortDuration | I66: 43374 | J66: NULL | K66: 1 | L66: EUR | M66: 688330 | N66: MSIM Short Duration Global Bond (CH Int Income) | O66: TRUE | P66: =IF(LEN(A66)>8,"TF","Del") -> Del | Q66: =IF(LEN(M66)>8,"TF","Del") -> Del
A67: 718930 | B67: 3882 | C67: Morgan Stanley | D67: DB6605 | E67: MBB GLOBAL SUSTAINABLE BOND | F67: FixedIncome | G67: Global | H67: Aggregate_ESG | I67: 45373 | J67: NULL | K67: 1 | L67: EUR | M67: 718930 | N67: MSIM Global Sustainable Bond | O67: TRUE | P67: =IF(LEN(A67)>8,"TF","Del") -> Del | Q67: =IF(LEN(M67)>8,"TF","Del") -> Del
A68: 689206 | B68: 1302 | C68: Morgan Stanley | D68: DB5200 | E68: CH INTERNATIONAL BOND | F68: FixedIncome | G68: Global | H68: Aggregate | I68: 43374 | J68: NULL | K68: 1 | L68: EUR | M68: 689206 | N68: MSIM Global Bond (CH Int Bond) | O68: TRUE | P68: =IF(LEN(A68)>8,"TF","Del") -> Del | Q68: =IF(LEN(M68)>8,"TF","Del") -> Del
A69: GFJ8 | B69: 4161 | C69: Muzinich | D69: CREA | E69: MGF EURO HIGH YIELD | F69: FixedIncome | G69: Europe | H69: HighYield | I69: 45723 | J69: NULL | K69: 1 | L69: EUR | M69: GFJ8 | N69: Muzinich European High Yield | O69: TRUE | P69: =IF(LEN(A69)>8,"TF","Del") -> Del | Q69: =IF(LEN(M69)>8,"TF","Del") -> Del
A70: 693779 | B70: 1541 | C70: Neuberger Berman | D70: DB6503 | E70: MBB EMERGING MARKETS FIXED INCOME | F70: FixedIncome | G70: EM | H70: HardCurrency | I70: 43595 | J70: NULL | K70: 1 | L70: EUR | M70: 693779 | N70: Neuberger Berman Emerging Market Debt Hard Currency | O70: TRUE | P70: =IF(LEN(A70)>8,"TF","Del") -> Del | Q70: =IF(LEN(M70)>8,"TF","Del") -> Del
A71: GFJW | B71: 2568 | C71: Neuberger Berman | D71: CHIN | E71: MGF GLOBALE MULTI BOND | F71: FixedIncome | G71: EM | H71: Blend | I71: 44599 | J71: NULL | K71: 1 | L71: EUR | M71: GFJW | N71: Neuberger Berman Emerging Market 50/50 Blend (GMB) | O71: TRUE | P71: =IF(LEN(A71)>8,"TF","Del") -> Del | Q71: =IF(LEN(M71)>8,"TF","Del") -> Del
A72: 689942 | B72: 1361 | C72: Neuberger Berman | D72: DB8820 | E72: CH EURO INCOME | F72: FixedIncome | G72: Europe | H72: Agg_Treasury | I72: 43405 | J72: NULL | K72: 1 | L72: EUR | M72: 689942 | N72: Neuberger Berman (Challenge Euro Income) | O72: TRUE | P72: =IF(LEN(A72)>8,"TF","Del") -> Del | Q72: =IF(LEN(M72)>8,"TF","Del") -> Del
A73: 727784 | B73: 4282 | C73: Neuberger Berman | D73: DB5555 | E73: MBB SOCIALLY RESPONSIBLE COLLECTION | F73: FixedIncome | G73: Europe | H73: Agg_Treasury | I73: 45783 | J73: NULL | K73: 0 | L73: EUR | M73: 689942 | N73: Neuberger Berman (Challenge Euro Income) | O73: FALSE | P73: =IF(LEN(A73)>8,"TF","Del") -> Del | Q73: =IF(LEN(M73)>8,"TF","Del") -> Del
A74: 728110 | B74: 4241 | C74: Ninety One | D74: DB8814 | E74: CH PACIFIC EQUITY | F74: Equity | G74: APAC | H74: Blend | I74: 45764 | J74: NULL | K74: 1 | L74: EUR | M74: LU1057489228 | N74: 91GSF-APEO-I ACC EUR | O74: FALSE | P74: =IF(LEN(A74)>8,"TF","Del") -> Del | Q74: =IF(LEN(M74)>8,"TF","Del") -> TF | R74: MIFL history is target fund investment, scope to adjust this to mandate
A75: 728114 | B75: 4242 | C75: Ninety One | D75: LU4133 | E75: GAMAX FUNDS ASIA PACIFIC | F75: Equity | G75: APAC | H75: Blend | I75: 45764 | J75: NULL | K75: 0 | L75: EUR | M75: LU1057489228 | N75: 91GSF-APEO-I ACC EUR | O75: FALSE | P75: =IF(LEN(A75)>8,"TF","Del") -> Del | Q75: =IF(LEN(M75)>8,"TF","Del") -> TF | R75: MIFL history is target fund investment, scope to adjust this to mandate
A76: 728111 | B76: 4181 | C76: Ninety One | D76: DB6501 | E76: MBB CHINESE ROAD OPPORTUNITIES | F76: Equity | G76: China | H76: Blend | I76: 45747 | J76: NULL | K76: 1 | L76: EUR | M76: LU1235249262 | N76: 91GSF-AL CHINA EQ-IACC USD | O76: FALSE | P76: =IF(LEN(A76)>8,"TF","Del") -> Del | Q76: =IF(LEN(M76)>8,"TF","Del") -> TF | R76: MIFL history is target fund investment, scope to adjust this to mandate
A77: 722431 | B77: 3921 | C77: OakHill | D77: DB3015 | E77: MBB GLOBAL HIGH YIELD | F77: FixedIncome | G77: Global | H77: HighYield | I77: 45455 | J77: NULL | K77: 1 | L77: USD | M77: 722431 | N77: Oak Hill US High Yield | O77: TRUE | P77: =IF(LEN(A77)>8,"TF","Del") -> Del | Q77: =IF(LEN(M77)>8,"TF","Del") -> Del
A78: 716679 | B78: 3521 | C78: PGIM | D78: DB6503 | E78: MBB EMERGING MARKETS FIXED INCOME | F78: FixedIncome | G78: EM | H78: LocalCurrency | I78: 45113 | J78: NULL | K78: 1 | L78: USD | M78: 716679 | N78: PGIM Emerging Market Local Currency | O78: TRUE | P78: =IF(LEN(A78)>8,"TF","Del") -> Del | Q78: =IF(LEN(M78)>8,"TF","Del") -> Del
A79: 716012 | B79: 3261 | C79: PGIM | D79: DB6503 | E79: MBB EMERGING MARKETS FIXED INCOME | F79: FixedIncome | G79: EM | H79: HighYield | I79: 45030 | J79: NULL | K79: 1 | L79: USD | M79: 666297 | N79: PGIM Emerging Market Debt Corporates | O79: FALSE | P79: =IF(LEN(A79)>8,"TF","Del") -> Del | Q79: =IF(LEN(M79)>8,"TF","Del") -> Del
A80: GFJX | B80: 2569 | C80: PGIM | D80: CHIN | E80: MGF GLOBALE MULTI BOND | F80: FixedIncome | G80: EM | H80: Blend | I80: 44599 | J80: NULL | K80: 1 | L80: EUR | M80: GFJX | N80: PGIM Emerging Market Blend | O80: TRUE | P80: =IF(LEN(A80)>8,"TF","Del") -> Del | Q80: =IF(LEN(M80)>8,"TF","Del") -> Del
A81: 666297 | B81: 932 | C81: PGIM | D81: DB3015 | E81: MBB GLOBAL HIGH YIELD | F81: FixedIncome | G81: US | H81: HighYield | I81: 42478 | J81: NULL | K81: 1 | L81: USD | M81: 666297 | N81: PGIM Emerging Market Debt Corporates | O81: TRUE | P81: =IF(LEN(A81)>8,"TF","Del") -> Del | Q81: =IF(LEN(M81)>8,"TF","Del") -> Del
A82: 713971 | B82: 3001 | C82: Pictet | D82: DB6574 | E82: MBB FUTURE SUSTAINABLE NUTRITION | F82: Equity | G82: Global | H82: Growth | I82: 45065 | J82: NULL | K82: 1 | L82: EUR | M82: 713971 | N82: Pictet Nutrition | O82: TRUE | P82: =IF(LEN(A82)>8,"TF","Del") -> Del | Q82: =IF(LEN(M82)>8,"TF","Del") -> Del
A83: 713421 | B83: 2823 | C83: Pictet | D83: DB6572 | E83: MBB ENERGY TRANSITION | F83: Equity | G83: Global | H83: Blend | I83: 44749 | J83: NULL | K83: 0 | L83: EUR | M83: 713421 | N83: Pictet Clean Energy | O83: TRUE | P83: =IF(LEN(A83)>8,"TF","Del") -> Del | Q83: =IF(LEN(M83)>8,"TF","Del") -> Del
A84: 708783 | B84: 2463 | C84: Pictet | D84: DB6544 | E84: MBB CIRCULAR ECONOMY OPPORTUNITIES | F84: Equity | G84: Global | H84: Blend | I84: 44568 | J84: NULL | K84: 1 | L84: EUR | M84: 708783 | N84: Pictet Circular Economy | O84: TRUE | P84: =IF(LEN(A84)>8,"TF","Del") -> Del | Q84: =IF(LEN(M84)>8,"TF","Del") -> Del
A85: 716844 | B85: 3481 | C85: Pinestone | D85: DB6592 | E85: MBB GLOBAL EQUITY STYLE SELECTION | F85: Equity | G85: Global | H85: Quality | I85: 45065 | J85: NULL | K85: 1 | L85: EUR | M85: 716844 | N85: PineStone Global Equity | O85: TRUE | P85: =IF(LEN(A85)>8,"TF","Del") -> Del | Q85: =IF(LEN(M85)>8,"TF","Del") -> Del
A86: 728109 | B86: 4263 | C86: Pinestone | D86: DB6502 | E86: MBB GLOBAL LEADERS | F86: Equity | G86: Global | H86: Quality | I86: 45771 | J86: NULL | K86: 0 | L86: EUR | M86: 716844 | N86: PineStone Global Equity | O86: FALSE | P86: =IF(LEN(A86)>8,"TF","Del") -> Del | Q86: =IF(LEN(M86)>8,"TF","Del") -> Del
A87: 727792 | B87: 4262 | C87: Pinestone | D87: DB4211 | E87: MBB EQUITY POWER COUPON COLLECTION | F87: Equity | G87: Global | H87: Quality | I87: 45771 | J87: NULL | K87: 0 | L87: EUR | M87: 716844 | N87: PineStone Global Equity | O87: FALSE | P87: =IF(LEN(A87)>8,"TF","Del") -> Del | Q87: =IF(LEN(M87)>8,"TF","Del") -> Del
A88: 729236 | B88: 4361 | C88: Putnam | D88: DB3784 | E88: CH HEALTHCARE EQUITY EVO. | F88: Equity | G88: Global | H88: Healthcare | I88: 45800 | J88: NULL | K88: 1 | L88: EUR | M88: 729236 | N88: Putnam Global Healthcare | O88: TRUE | P88: =IF(LEN(A88)>8,"TF","Del") -> Del | Q88: =IF(LEN(M88)>8,"TF","Del") -> Del
A89: 716543 | B89: 3482 | C89: Pzena | D89: DB6592 | E89: MBB GLOBAL EQUITY STYLE SELECTION | F89: Equity | G89: Global | H89: Value_Concentrated | I89: 45065 | J89: NULL | K89: 1 | L89: EUR | M89: 716543 | N89: Pzena Global Focused Value | O89: TRUE | P89: =IF(LEN(A89)>8,"TF","Del") -> Del | Q89: =IF(LEN(M89)>8,"TF","Del") -> Del
A90: 706632 | B90: 2261 | C90: Pzena | D90: DB6342 | E90: MBB DYNAMIC INTERNATIONAL VALUE OPPORTUNITIES | F90: Equity | G90: Global | H90: Value | I90: 44368 | J90: NULL | K90: 1 | L90: EUR | M90: 706632 | N90: Pzena Global Value | O90: TRUE | P90: =IF(LEN(A90)>8,"TF","Del") -> Del | Q90: =IF(LEN(M90)>8,"TF","Del") -> Del
A91: 726053 | B91: 4221 | C91: Robeco | D91: DB8814 | E91: CH PACIFIC EQUITY | F91: Equity | G91: APAC | H91: Value | I91: 45758 | J91: NULL | K91: 1 | L91: EUR | M91: LU1493701376 | N91: ROBECO ASIA PAC EQ-I ACC EUR | O91: FALSE | P91: =IF(LEN(A91)>8,"TF","Del") -> Del | Q91: =IF(LEN(M91)>8,"TF","Del") -> TF | R91: MIFL history is target fund investment, scope to adjust this to mandate
A92: 726054 | B92: 4222 | C92: Robeco | D92: LU4133 | E92: GAMAX FUNDS ASIA PACIFIC | F92: Equity | G92: APAC | H92: Value | I92: 45758 | J92: NULL | K92: 0 | L92: EUR | M92: LU1493701376 | N92: ROBECO ASIA PAC EQ-I ACC EUR | O92: FALSE | P92: =IF(LEN(A92)>8,"TF","Del") -> Del | Q92: =IF(LEN(M92)>8,"TF","Del") -> TF | R92: MIFL history is target fund investment, scope to adjust this to mandate
A93: 727786 | B93: 4243 | C93: Robeco | D93: DB5434 | E93: MBB COUPON STRATEGY COLLECTION | F93: Equity | G93: EM | H93: Value | I93: 45770 | J93: NULL | K93: 0 | L93: EUR | M93: 684489 | N93: Robeco Emerging Market Equities | O93: FALSE | P93: =IF(LEN(A93)>8,"TF","Del") -> Del | Q93: =IF(LEN(M93)>8,"TF","Del") -> Del
A94: 682591 | B94: 1125 | C94: Robeco | D94: DB3019 | E94: MBB EMERGING MARKETS COLLECTION | F94: Equity | G94: EM | H94: Value | I94: 43087 | J94: NULL | K94: 1 | L94: EUR | M94: 684489 | N94: Robeco Emerging Market Equities | O94: FALSE | P94: =IF(LEN(A94)>8,"TF","Del") -> Del | Q94: =IF(LEN(M94)>8,"TF","Del") -> Del
A95: 684489 | B95: 1141 | C95: Robeco | D95: DB8816 | E95: CH EMERGING MARKETS EQUITY | F95: Equity | G95: EM | H95: Value | I95: 43200 | J95: NULL | K95: 0 | L95: EUR | M95: 684489 | N95: Robeco Emerging Market Equities | O95: TRUE | P95: =IF(LEN(A95)>8,"TF","Del") -> Del | Q95: =IF(LEN(M95)>8,"TF","Del") -> Del
A96: 682590 | B96: 1124 | C96: Robeco | D96: DB5555 | E96: MBB SOCIALLY RESPONSIBLE COLLECTION | F96: Equity | G96: Global | H96: Quality | I96: 43087 | J96: NULL | K96: 1 | L96: EUR | M96: 682590 | N96: Robeco Sustainable Global Stars | O96: TRUE | P96: =IF(LEN(A96)>8,"TF","Del") -> Del | Q96: =IF(LEN(M96)>8,"TF","Del") -> Del
A97: 718931 | B97: 3842 | C97: Robeco | D97: DB6604 | E97: MBB GREEN BUILDINGS EVO. | F97: Equity | G97: Global | H97: GreenBuildings | I97: 45373 | J97: NULL | K97: 1 | L97: EUR | M97: 718931 | N97: Robeco Green Buildings | O97: TRUE | P97: =IF(LEN(A97)>8,"TF","Del") -> Del | Q97: =IF(LEN(M97)>8,"TF","Del") -> Del
A98: Robeco1_6124 | B98: 2761 | C98: Robeco | D98: FIBAN024 | E98: MG COMPROMISO | F98: Equity | G98: Global | H98: Blend | I98: 43930 | J98: NULL | K98: 1 | L98: EUR | O98: FALSE | P98: =IF(LEN(A98)>8,"TF","Del") -> TF | Q98: =IF(LEN(M98)>8,"TF","Del") -> Del
A99: 716926 | B99: 3581 | C99: Sanders | D99: DB6342 | E99: MBB DYNAMIC INTERNATIONAL VALUE OPPORTUNITIES | F99: Equity | G99: Global | H99: Value | I99: 45121 | J99: NULL | K99: 0 | L99: EUR | M99: 716958 | N99: Sanders Capital Global Value | O99: FALSE | P99: =IF(LEN(A99)>8,"TF","Del") -> Del | Q99: =IF(LEN(M99)>8,"TF","Del") -> Del
A100: 716958 | B100: 3483 | C100: Sanders | D100: DB6592 | E100: MBB GLOBAL EQUITY STYLE SELECTION | F100: Equity | G100: Global | H100: Value | I100: 45065 | J100: NULL | K100: 1 | L100: EUR | M100: 716958 | N100: Sanders Capital Global Value | O100: TRUE | P100: =IF(LEN(A100)>8,"TF","Del") -> Del | Q100: =IF(LEN(M100)>8,"TF","Del") -> Del
A101: 716406 | B101: 3321 | C101: Sands | D101: DB6459 | E101: MBB INNOVATIVE THEMATIC OPPORTUNITIES | F101: Equity | G101: Global | H101: Growth | I101: 45030 | J101: NULL | K101: 1 | L101: EUR | M101: 716406 | N101: Sands Capital Global Growth | O101: TRUE | P101: =IF(LEN(A101)>8,"TF","Del") -> Del | Q101: =IF(LEN(M101)>8,"TF","Del") -> Del
A102: 693764 | B102: 1542 | C102: Schroders | D102: DB6501 | E102: MBB CHINESE ROAD OPPORTUNITIES | F102: Equity | G102: China | H102: Blend | I102: 43595 | J102: NULL | K102: 1 | L102: EUR | M102: 693764 | N102: Schroders China Opportunities | O102: TRUE | P102: =IF(LEN(A102)>8,"TF","Del") -> Del | Q102: =IF(LEN(M102)>8,"TF","Del") -> Del
A103: 700087 | B103: 1822 | C103: Schroders | D103: DB6484 | E103: MBB GLOBAL DEMOGRAPHIC OPPORTUNITIES | F103: Equity | G103: Global | H103: Growth | I103: 44026 | J103: NULL | K103: 1 | L103: EUR | M103: 700087 | N103: Schroders Global Demographics | O103: TRUE | P103: =IF(LEN(A103)>8,"TF","Del") -> Del | Q103: =IF(LEN(M103)>8,"TF","Del") -> Del
A104: 718929 | B104: 3861 | C104: Schroders | D104: DB6604 | E104: MBB GREEN BUILDINGS EVO. | F104: Equity | G104: Global | H104: GreenBuildings | I104: 45373 | J104: NULL | K104: 1 | L104: EUR | M104: 718929 | N104: Schroders Green Buildings | O104: TRUE | P104: =IF(LEN(A104)>8,"TF","Del") -> Del | Q104: =IF(LEN(M104)>8,"TF","Del") -> Del
A105: 713408 | B105: 2822 | C105: Schroders | D105: DB6572 | E105: MBB ENERGY TRANSITION | F105: Equity | G105: Global | H105: Blend | I105: 44749 | J105: NULL | K105: 0 | L105: EUR | M105: 713408 | N105: Schroders Global Energy Transition | O105: TRUE | P105: =IF(LEN(A105)>8,"TF","Del") -> Del | Q105: =IF(LEN(M105)>8,"TF","Del") -> Del
A106: 700206 | B106: 1801 | C106: Schroders | D106: DB8824 | E106: CH PROVIDENT 1 | F106: Equity | G106: Global | H106: Blend | I106: 44060 | J106: NULL | K106: 1 | L106: EUR | M106: 700206 | N106: Schroders Global Equity | O106: TRUE | P106: =IF(LEN(A106)>8,"TF","Del") -> Del | Q106: =IF(LEN(M106)>8,"TF","Del") -> Del
A107: 709785 | B107: 2541 | C107: Schroders | D107: DB4223 | E107: CH INTERNATIONAL EQUITY | F107: Equity | G107: Global | H107: Blend | I107: 44540 | J107: NULL | K107: 0 | L107: EUR | M107: 700206 | N107: Schroders Global Equity | O107: FALSE | P107: =IF(LEN(A107)>8,"TF","Del") -> Del | Q107: =IF(LEN(M107)>8,"TF","Del") -> Del
A108: 704620 | B108: 1981 | C108: SGA | D108: DB8816 | E108: CH EMERGING MARKETS EQUITY | F108: Equity | G108: EM | H108: Growth | I108: 44235 | J108: NULL | K108: 1 | L108: EUR | M108: 704620 | N108: SGA Global Emerging Market Equity | O108: TRUE | P108: =IF(LEN(A108)>8,"TF","Del") -> Del | Q108: =IF(LEN(M108)>8,"TF","Del") -> Del
A109: 645766 | B109: 881 | C109: Tenax | D109: DB3787 | E109: CH FINANCIAL EQUITY EVO. | F109: Equity | G109: Global | H109: Sec_Financial | I109: 41492 | J109: NULL | K109: 1 | L109: EUR | M109: 645766 | N109: Tenax Financial Equity | O109: TRUE | P109: =IF(LEN(A109)>8,"TF","Del") -> Del | Q109: =IF(LEN(M109)>8,"TF","Del") -> Del
A110: 596994 | B110: 892 | C110: Trea | D110: DB4221 | E110: CH SPAIN EQUITY | F110: Equity | G110: Spain | H110: Blend | I110: 39451 | J110: NULL | K110: 1 | L110: EUR | M110: 596994 | N110: Trea Spain Equity | O110: TRUE | P110: =IF(LEN(A110)>8,"TF","Del") -> Del | Q110: =IF(LEN(M110)>8,"TF","Del") -> Del
... A119: 724730 | B119: 4122 | C119: Zazove | D119: DB2016 | E119: MBB CONVERTIBLE STRATEGY COLLECTION | F119: Hybrid | G119: Global | H119: Blend | I119: 45632 | J119: NULL | K119: 1 | L119: USD | M119: 724730 | N119: Zazove Global Convertible | O119: TRUE | P119: =IF(LEN(A119)>8,"TF","Del") -> Del | Q119: =IF(LEN(M119)>8,"TF","Del") -> Del
A120: LU2444715366 | C120: HRFDS-360 ONE FCSD IND-B1USD | L120: USD | M120: LU2444715366 | N120: 360 One India | O120: TRUE | P120: =IF(LEN(A120)>8,"TF","Del") -> TF | Q120: =IF(LEN(M120)>8,"TF","Del") -> TF
A121: LU0840615578 | C121: ALLIANZ GERMAN EQUITY-IT | L121: EUR | M121: LU0840615578 | N121: Allianz Germany | O121: TRUE | P121: =IF(LEN(A121)>8,"TF","Del") -> TF | Q121: =IF(LEN(M121)>8,"TF","Del") -> TF
A122: LU2106854214 | C122: ALLIANZ THEMATICA-WT EUR A | L122: EUR | M122: LU2106854214 | N122: Allianz Thematica | O122: TRUE | P122: =IF(LEN(A122)>8,"TF","Del") -> TF | Q122: =IF(LEN(M122)>8,"TF","Del") -> TF
A123: LU1870374508 | C123: ALMA CAP-AL EI JP LCE-IEURC | L123: EUR | M123: LU1870374508 | N123: Alma Eikoh Japan | O123: TRUE | P123: =IF(LEN(A123)>8,"TF","Del") -> TF | Q123: =IF(LEN(M123)>8,"TF","Del") -> TF
A124: IE00B615T757 | C124: ARTISAN-GLOBAL OPP-I- USD-AC | L124: USD | M124: IE00B615T757 | N124: Artisan Global Opportunities | O124: TRUE | P124: =IF(LEN(A124)>8,"TF","Del") -> TF | Q124: =IF(LEN(M124)>8,"TF","Del") -> TF
A125: IE00B4M6YD48 | C125: ARTISAN GLOBL VALUE FND-IEUR | L125: EUR | M125: IE00B4M6YD48 | N125: Artisan Global Value | O125: TRUE | P125: =IF(LEN(A125)>8,"TF","Del") -> TF | Q125: =IF(LEN(M125)>8,"TF","Del") -> TF
A126: IE00BKTZQN06 | C126: ATLAS GLOBAL INFRASTRU-B EUR | L126: EUR | M126: IE00BKTZQN06 | N126: Atlas Global Infrastructure | O126: TRUE | P126: =IF(LEN(A126)>8,"TF","Del") -> TF | Q126: =IF(LEN(M126)>8,"TF","Del") -> TF
A127: LU2200556392 | C127: HEREFORD-BIN YUAN GRC-DI A U | L127: USD | M127: LU2200556392 | N127: Bin Yuan All China | O127: TRUE | P127: =IF(LEN(A127)>8,"TF","Del") -> TF | Q127: =IF(LEN(M127)>8,"TF","Del") -> TF
A128: LU2041044764 | C128: BGF-CIRCULAR ECONOMY-I2 EUR | L128: EUR | M128: LU2041044764 | N128: BlackRock Circular Economy | O128: TRUE | P128: =IF(LEN(A128)>8,"TF","Del") -> TF | Q128: =IF(LEN(M128)>8,"TF","Del") -> TF
...

Sheet Sheet2
A1: MsMap
A2: 708786 | B2: =VLOOKUP(A2,FinalMap!B:B,1,0) -> 708786
A3: 724767 | B3: =VLOOKUP(A3,FinalMap!B:B,1,0) -> 724767
A4: 657375 | B4: =VLOOKUP(A4,FinalMap!B:B,1,0) -> 657375
A5: 719168 | B5: =VLOOKUP(A5,FinalMap!B:B,1,0) -> 719168
A6: 719169 | B6: =VLOOKUP(A6,FinalMap!B:B,1,0) -> 719169
A7: 597012 | B7: =VLOOKUP(A7,FinalMap!B:B,1,0) -> 597012
A8: 597016 | B8: =VLOOKUP(A8,FinalMap!B:B,1,0) -> 597016
A9: 686585 | B9: =VLOOKUP(A9,FinalMap!B:B,1,0) -> 686585
A10: 597009 | B10: =VLOOKUP(A10,FinalMap!B:B,1,0) -> 597009
A11: 724627 | B11: =VLOOKUP(A11,FinalMap!B:B,1,0) -> 724627
A12: 716407 | B12: =VLOOKUP(A12,FinalMap!B:B,1,0) -> 716407
A13: 714548 | B13: =VLOOKUP(A13,FinalMap!B:B,1,0) -> 714548
... A17: 689939 | B17: =VLOOKUP(A17,FinalMap!B:B,1,0) -> 689939
A18: GFJQ | B18: =VLOOKUP(A18,FinalMap!B:B,1,0) -> GFJQ
A19: 722285 | B19: =VLOOKUP(A19,FinalMap!B:B,1,0) -> 722285
A20: 692350 | B20: =VLOOKUP(A20,FinalMap!B:B,1,0) -> 692350
A21: GFJY | B21: =VLOOKUP(A21,FinalMap!B:B,1,0) -> GFJY
A22: 642651 | B22: =VLOOKUP(A22,FinalMap!B:B,1,0) -> 642651
A23: 596990 | B23: =VLOOKUP(A23,FinalMap!B:B,1,0) -> 596990
A24: 681724 | B24: =VLOOKUP(A24,FinalMap!B:B,1,0) -> 681724
A25: 712560 | B25: =VLOOKUP(A25,FinalMap!B:B,1,0) -> 712560
A26: 711342 | B26: =VLOOKUP(A26,FinalMap!B:B,1,0) -> 711342
A27: 718928 | B27: =VLOOKUP(A27,FinalMap!B:B,1,0) -> 718928
A28: 714703 | B28: =VLOOKUP(A28,FinalMap!B:B,1,0) -> 714703
A29: 707638 | B29: =VLOOKUP(A29,FinalMap!B:B,1,0) -> 707638
A30: 722394 | B30: =VLOOKUP(A30,FinalMap!B:B,1,0) -> 722394
A31: 716405 | B31: =VLOOKUP(A31,FinalMap!B:B,1,0) -> 716405
A32: 708787 | B32: =VLOOKUP(A32,FinalMap!B:B,1,0) -> 708787
A33: 714113 | B33: =VLOOKUP(A33,FinalMap!B:B,1,0) -> 714113
... A42: 716863 | B42: =VLOOKUP(A42,FinalMap!B:B,1,0) -> 716863
A43: GFJ9 | B43: =VLOOKUP(A43,FinalMap!B:B,1,0) -> GFJ9
A44: 720798 | B44: =VLOOKUP(A44,FinalMap!B:B,1,0) -> 720798
A45: 714941 | B45: =VLOOKUP(A45,FinalMap!B:B,1,0) -> 714941
A46: 682588 | B46: =VLOOKUP(A46,FinalMap!B:B,1,0) -> #N/A
A47: 688330 | B47: =VLOOKUP(A47,FinalMap!B:B,1,0) -> 688330
A48: 718930 | B48: =VLOOKUP(A48,FinalMap!B:B,1,0) -> 718930
A49: 689206 | B49: =VLOOKUP(A49,FinalMap!B:B,1,0) -> 689206
A50: GFJ8 | B50: =VLOOKUP(A50,FinalMap!B:B,1,0) -> GFJ8
A51: 693779 | B51: =VLOOKUP(A51,FinalMap!B:B,1,0) -> 693779
A52: GFJW | B52: =VLOOKUP(A52,FinalMap!B:B,1,0) -> GFJW
A53: 689942 | B53: =VLOOKUP(A53,FinalMap!B:B,1,0) -> 689942
A54: LU1057489228 | B54: =VLOOKUP(A54,FinalMap!B:B,1,0) -> LU1057489228
A55: LU1235249262 | B55: =VLOOKUP(A55,FinalMap!B:B,1,0) -> LU1235249262
A56: 722431 | B56: =VLOOKUP(A56,FinalMap!B:B,1,0) -> 722431
A57: 716679 | B57: =VLOOKUP(A57,FinalMap!B:B,1,0) -> 716679
A58: 666297 | B58: =VLOOKUP(A58,FinalMap!B:B,1,0) -> 666297
A59: GFJX | B59: =VLOOKUP(A59,FinalMap!B:B,1,0) -> GFJX
A60: 713971 | B60: =VLOOKUP(A60,FinalMap!B:B,1,0) -> 713971
A61: 713421 | B61: =VLOOKUP(A61,FinalMap!B:B,1,0) -> 713421
A62: 708783 | B62: =VLOOKUP(A62,FinalMap!B:B,1,0) -> 708783
A63: 716844 | B63: =VLOOKUP(A63,FinalMap!B:B,1,0) -> 716844
A64: 729236 | B64: =VLOOKUP(A64,FinalMap!B:B,1,0) -> 729236
A65: 716543 | B65: =VLOOKUP(A65,FinalMap!B:B,1,0) -> #N/A
A66: 706632 | B66: =VLOOKUP(A66,FinalMap!B:B,1,0) -> 706632
A67: LU1493701376 | B67: =VLOOKUP(A67,FinalMap!B:B,1,0) -> LU1493701376
A68: 684489 | B68: =VLOOKUP(A68,FinalMap!B:B,1,0) -> 684489
A69: 682590 | B69: =VLOOKUP(A69,FinalMap!B:B,1,0) -> 682590
A70: 718931 | B70: =VLOOKUP(A70,FinalMap!B:B,1,0) -> 718931
A71: 716958 | B71: =VLOOKUP(A71,FinalMap!B:B,1,0) -> 716958
A72: 716406 | B72: =VLOOKUP(A72,FinalMap!B:B,1,0) -> 716406
A73: 693764 | B73: =VLOOKUP(A73,FinalMap!B:B,1,0) -> 693764
A74: 700087 | B74: =VLOOKUP(A74,FinalMap!B:B,1,0) -> 700087
A75: 718929 | B75: =VLOOKUP(A75,FinalMap!B:B,1,0) -> 718929
A76: 713408 | B76: =VLOOKUP(A76,FinalMap!B:B,1,0) -> 713408
A77: 700206 | B77: =VLOOKUP(A77,FinalMap!B:B,1,0) -> 700206
A78: 704620 | B78: =VLOOKUP(A78,FinalMap!B:B,1,0) -> 704620
A79: 645766 | B79: =VLOOKUP(A79,FinalMap!B:B,1,0) -> 645766
... A87: 724730 | B87: =VLOOKUP(A87,FinalMap!B:B,1,0) -> 724730
A88: LU2444715366 | B88: =VLOOKUP(A88,FinalMap!B:B,1,0) -> LU2444715366
A89: LU0840615578 | B89: =VLOOKUP(A89,FinalMap!B:B,1,0) -> LU0840615578
A90: LU2106854214 | B90: =VLOOKUP(A90,FinalMap!B:B,1,0) -> #N/A
A91: LU1870374508 | B91: =VLOOKUP(A91,FinalMap!B:B,1,0) -> LU1870374508
A92: IE00B615T757 | B92: =VLOOKUP(A92,FinalMap!B:B,1,0) -> IE00B615T757
A93: IE00B4M6YD48 | B93: =VLOOKUP(A93,FinalMap!B:B,1,0) -> IE00B4M6YD48
A94: IE00BKTZQN06 | B94: =VLOOKUP(A94,FinalMap!B:B,1,0) -> IE00BKTZQN06
A95: LU2200556392 | B95: =VLOOKUP(A95,FinalMap!B:B,1,0) -> LU2200556392
A96: LU2041044764 | B96: =VLOOKUP(A96,FinalMap!B:B,1,0) -> LU2041044764
A97: LU1505937943 | B97: =VLOOKUP(A97,FinalMap!B:B,1,0) -> LU1505937943
A98: LU1616921232 | B98: =VLOOKUP(A98,FinalMap!B:B,1,0) -> LU1616921232
A99: LU1920210579 | B99: =VLOOKUP(A99,FinalMap!B:B,1,0) -> LU1920210579
... A130: LU0396332214 | B130: =VLOOKUP(A130,FinalMap!B:B,1,0) -> LU0396332214

Sheet SAA_Map_Breakdown
A1: Change Date | B1: ID_Code | C1: Weight | D1: SAA | E1: PreMerge_BlendID | F1: Type | G1: IsComposite | H1: Provider | I1: Ticker | J1: Comment | K1: IAR SAA | L1: Currency | M1: Hedged.Status | N1: IAR SAA
A2: 1 | B2: 596990 | C2: 85 | D2: MSCI Germany | E2: MS_RagSAA21 | F2: Del | P2: =IF(K2<>"",N2=D2,"")
A3: 1 | B3: 596990 | C3: 15 | D3: MSCI Germany Small Cap | E3: MS_RagSAA21 | F3: Del | P3: =IF(K3<>"",N3=D3,"")
A4: 1 | B4: 596994 | C4: 80 | D4: MSCI Spain 10/40 | E4: MS_RagSAA70 | F4: Del | P4: =IF(K4<>"",N4=D4,"")
A5: 1 | B5: 596994 | C5: 20 | D5: MSCI Spain Small Cap | E5: MS_RagSAA70 | F5: Del | P5: =IF(K5<>"",N5=D5,"")
A6: 1 | B6: 596998 | C6: 100 | D6: MSCI World | E6: MS_RagSAA76 | F6: Del | P6: =IF(K6<>"",N6=D6,"")
A7: 1 | B7: 597009 | C7: 100 | D7: MSCI USA | E7: MS_RagSAA10 | F7: Del | P7: =IF(K7<>"",N7=D7,"")
A8: 1 | B8: 597012 | C8: 100 | D8: MSCI AC Asia Pacific | E8: MS_RagSAA9 | F8: Del | P8: =IF(K8<>"",N8=D8,"")
A9: 1 | B9: 597016 | C9: 100 | D9: MSCI EM | E9: MS_RagSAA7 | F9: Del | P9: =IF(K9<>"",N9=D9,"")
A10: 1 | B10: 642651 | C10: 100 | D10: DJE GAMAX Junior SAA | E10: MS_RagSAA20 | F10: Del | P10: =IF(K10<>"",N10=D10,"")
A11: 1 | B11: 645766 | C11: 100 | D11: MSCI World Financials | E11: MS_RagSAA69 | F11: Del | P11: =IF(K11<>"",N11=D11,"")
A12: 1 | B12: 657375 | C12: 15 | D12: MSCI World Financial Index local currencies (NDWLFNCL Index) perfectly hedged | E12: MS_RagSAA79 | F12: Del | P12: =IF(K12<>"",N12=D12,"")
A13: 1 | B13: 657375 | C13: 25 | D13: The BofA Merrill Lynch Contingent Capital Index EUR hedged (COCO Index) | E13: MS_RagSAA79 | F13: Del | P13: =IF(K13<>"",N13=D13,"")
... A102: 1 | B102: 724767 | C102: 100 | D102: Refinitiv Global Focus Hgd CB TR USD | E102: MS_RagSAA116 | F102: Del | P102: =IF(K102<>"",N102=D102,"")
A103: 1 | B103: FR0000974149 | C103: 100 | D103: MSCI Europe SMID Growth | E103: MS_RagSAA50 | F103: TF | G103: FALSE | K103: #N/A | L103: #N/A | M103: #N/A | N103: #N/A | P103: =IF(K103<>"",N103=D103,"") -> #N/A
A104: 1 | B104: FR0013429446 | C104: 100 | D104: Refinitiv Global Focus Hgd CB TR USD | E104: MS_RagSAA98 | F104: TF | G104: FALSE | K104: UCBIFX02 Index | L104: USD | M104: Y | N104: FTSE Global Focus Convertible Hedged CB (USD) | P104: =IF(K104<>"",N104=D104,"") -> FALSE
A105: 1 | B105: GFJ9 | C105: 100 | D105: MAN GLG European High Yield - SAA | E105: MS_RagSAA112 | F105: Del | P105: =IF(K105<>"",N105=D105,"")
A106: 1 | B106: GFJQ | C106: 100 | D106: ICE BofA Global Corporate Index (G0BC) | E106: MS_RagSAA81 | F106: Del | P106: =IF(K106<>"",N106=D106,"")
A107: 1 | B107: GFJW | C107: 100 | D107: NB GMB - SAA | E107: MS_RagSAA94 | F107: Del | P107: =IF(K107<>"",N107=D107,"")
A108: 1 | B108: GFJX | C108: 100 | D108: PGIM EM Blend - SAA | E108: MS_RagSAA96 | F108: Del | P108: =IF(K108<>"",N108=D108,"")
A109: 1 | B109: GFJY | C109: 100 | D109: C4 Composite: ICE European Currency High Yield, then 31/03/2022 | E109: MS_RagSAA85 | F109: Del | P109: =IF(K109<>"",N109=D109,"")
A110: 44652 | B110: GFJY | C110: 65 | D110: HPC0 | E110: MS_RagSAA85 | F110: Del | P110: =IF(K110<>"",N110=D110,"")
A111: 44652 | B111: GFJY | C111: 35 | D111: JUC0 | E111: MS_RagSAA85 | F111: Del | P111: =IF(K111<>"",N111=D111,"")
A112: 1 | B112: IE00027GCDQ6 | C112: 70 | D112: ICE BB-B Global High Yield - HW40 | E112: MS_RagSAA101 | F112: TF | G112: TRUE | K112: GBMI Index | L112: EUR | M112: Y | N112: ICE BofAML Global Broad Market | P112: =IF(K112<>"",N112=D112,"") -> FALSE
A113: 1 | B113: IE00027GCDQ6 | C113: 30 | D113: ICE BBB Global Corporate - GBC4 | E113: MS_RagSAA101 | F113: TF | G113: TRUE | K113: GBMI Index | L113: EUR | M113: Y | N113: ICE BofAML Global Broad Market | P113: =IF(K113<>"",N113=D113,"") -> FALSE
A114: 1 | B114: IE0007LWGYY1 | C114: 100 | D114: 50/50 JPM EM Blend (EUR) | E114: MS_RagSAA78 | F114: TF | G114: FALSE | K114: WALD Index | L114: USD | M114: N | N114: ICE BofAML Diversified Emerging Markets Sovereign Bond | P114: =IF(K114<>"",N114=D114,"") -> FALSE
A115: 45809 | B115: IE0007LWGYY1 | C115: 50 | D115: ICE BofAML US Emerging Markets External Sovereign | E115: MS_RagSAA78 | F115: TF | G115: TRUE | H115: ICE | I115: DGOV Index | J115: Changed due to License | K115: WALD Index | L115: USD | M115: N | N115: ICE BofAML Diversified Emerging Markets Sovereign Bond | P115: =IF(K115<>"",N115=D115,"") -> FALSE
A116: 45809 | B116: IE0007LWGYY1 | C116: 50 | D116: ICE BofAML Diversified Emerging Markets Sovereign Bond | E116: MS_RagSAA78 | F116: TF | G116: TRUE | H116: ICE | I116: WALD Index | J116: Changed due to License | K116: WALD Index | L116: USD | M116: N | N116: ICE BofAML Diversified Emerging Markets Sovereign Bond | P116: =IF(K116<>"",N116=D116,"") -> TRUE
A117: 1 | B117: IE00B3DJ5M15 | C117: 100 | D117: MSCI EM | E117: MS_RagSAA37 | F117: TF | G117: FALSE | K117: MXEF Index | L117: EUR | M117: N | N117: MSCI EM | P117: =IF(K117<>"",N117=D117,"") -> TRUE
A118: 1 | B118: IE00B4M6YD48 | C118: 100 | D118: MSCI ACWI Value | E118: MS_RagSAA12 | F118: TF | G118: FALSE | K118: MXWD Index | L118: EUR | M118: N | N118: MSCI AC World | P118: =IF(K118<>"",N118=D118,"") -> FALSE
A119: 1 | B119: IE00B615T757 | C119: 100 | D119: MSCI ACWI Growth | E119: MS_RagSAA11 | F119: TF | G119: FALSE | K119: MXWD Index | L119: USD | M119: N | N119: MSCI AC World | P119: =IF(K119<>"",N119=D119,"") -> FALSE
A120: 1 | B120: IE00BF21WN20 | C120: 100 | D120: MSCI EM Growth | E120: MS_RagSAA62 | F120: TF | G120: FALSE | K120: MXEF Index | L120: EUR | M120: N | N120: MSCI Emerging Markets | P120: =IF(K120<>"",N120=D120,"") -> FALSE
A121: 1 | B121: IE00BFY85J84 | C121: 100 | D121: FTSE Global Core 50/50 | E121: MS_RagSAA31 | F121: TF | G121: FALSE | K121: M8CXRARA Index | L121: EUR | M121: N | N121: MSCI World Core Infrastructure | P121: =IF(K121<>"",N121=D121,"") -> FALSE
A122: 45809 | B122: IE00BFY85J84 | C122: 100 | D122: MSCI World Core Infrastructure | E122: MS_RagSAA31 | F122: TF | G122: FALSE | H122: MSCI | I122: M8CXRARA Index | J122: Changed due to License | K122: M8CXRARA Index | L122: EUR | M122: N | N122: MSCI World Core Infrastructure | P122: =IF(K122<>"",N122=D122,"") -> TRUE
A123: 1 | B123: IE00BKTZQN06 | C123: 50 | D123: FTSE Global Core 50/50 | E123: MS_RagSAA13 | F123: TF | G123: TRUE | K123: M8CXRARA Index | L123: EUR | M123: N | N123: MSCI World Core Infrastructure | P123: =IF(K123<>"",N123=D123,"") -> FALSE
A124: 1 | B124: IE00BKTZQN06 | C124: 50 | D124: S&P Global Infrastructure | E124: MS_RagSAA13 | F124: TF | G124: TRUE | K124: M8CXRARA Index | L124: EUR | M124: N | N124: MSCI World Core Infrastructure | P124: =IF(K124<>"",N124=D124,"") -> FALSE
A125: 45809 | B125: IE00BKTZQN06 | C125: 100 | D125: MSCI World Core Infrastructure | E125: MS_RagSAA13 | F125: TF | G125: FALSE | H125: MSCI | I125: M8CXRARA Index | J125: Changed due to License | K125: M8CXRARA Index | L125: EUR | M125: N | N125: MSCI World Core Infrastructure | P125: =IF(K125<>"",N125=D125,"") -> TRUE
A126: 1 | B126: IE00BM99WQ17 | C126: 100 | D126: JPM EMBI Global Diversified | E126: MS_RagSAA80 | F126: TF | G126: FALSE | K126: DGOV Index | L126: EUR | M126: N | N126: ICE BofAML US Emerging Markets External Sovereign | P126: =IF(K126<>"",N126=D126,"") -> FALSE
A127: 1 | B127: IE00BMWVYP76 | C127: 100 | D127: Refinitiv Global Focus Hgd CB TR USD | E127: MS_RagSAA99 | F127: TF | G127: FALSE | K127: UCBIFX02 Index | L127: USD | M127: Y | N127: FTSE Global Focus Convertible Hedged CB (USD) | P127: =IF(K127<>"",N127=D127,"") -> FALSE
A128: 1 | B128: IE00BNHQBY28 | C128: 100 | D128: FTSE Global Core 50/50 | E128: MS_RagSAA71 | F128: TF | G128: FALSE | K128: M8CXRARA Index | L128: EUR | M128: N | N128: MSCI World Core Infrastructure | P128: =IF(K128<>"",N128=D128,"") -> FALSE
A129: 45809 | B129: IE00BNHQBY28 | C129: 100 | D129: MSCI World Core Infrastructure | E129: MS_RagSAA71 | F129: TF | G129: FALSE | H129: MSCI | I129: M8CXRARA Index | J129: Changed due to License | K129: M8CXRARA Index | L129: EUR | M129: N | N129: MSCI World Core Infrastructure | P129: =IF(K129<>"",N129=D129,"") -> TRUE
A130: 1 | B130: IE00BYXW3909 | C130: 100 | D130: MSCI China All Shares | E130: MS_RagSAA115 | F130: TF | G130: FALSE | K130: MXCNANM Index | L130: EUR | M130: N | N130: MSCI China All Shares | P130: =IF(K130<>"",N130=D130,"") -> TRUE
A131: 1 | B131: IE00BZCG7W10 | C131: 100 | D131: JPM EMBI Global Diversified (USD) | E131: MS_RagSAA103 | F131: TF | G131: FALSE | K131: DGOV Index | L131: USD | M131: N | N131: ICE BofAML US Emerging Markets External Sovereign | P131: =IF(K131<>"",N131=D131,"") -> FALSE
A132: 45809 | B132: IE00BZCG7W10 | C132: 100 | D132: ICE BofAML US Emerging Markets External Sovereign | E132: MS_RagSAA103 | F132: TF | G132: FALSE | H132: ICE | I132: DGOV Index | J132: Changed due to License | K132: DGOV Index | L132: USD | M132: N | N132: ICE BofAML US Emerging Markets External Sovereign | P132: =IF(K132<>"",N132=D132,"") -> TRUE
A133: 1 | B133: LU0396332214 | C133: 100 | D133: Refinitiv Gbl Vanilla Hgd CB TR EUR | E133: MS_RagSAA100 | F133: TF | G133: FALSE | K133: UCBIFX15 Index | L133: EUR | M133: Y | N133: Refinitiv Global Vanilla Hedged (CB) Euro | P133: =IF(K133<>"",N133=D133,"") -> FALSE
A134: 1 | B134: LU0399027886 | C134: 80 | D134: ICE Global Broad Markets EUR Hedged (GBMI) | E134: MS_RagSAA87 | F134: TF | G134: TRUE | K134: #N/A | L134: #N/A | M134: #N/A | N134: #N/A | P134: =IF(K134<>"",N134=D134,"") -> #N/A
A135: 1 | B135: LU0399027886 | C135: 20 | D135: ICE Global HY Constrained EUR Hedged (HW0C) | E135: MS_RagSAA87 | F135: TF | G135: TRUE | K135: #N/A | L135: #N/A | M135: #N/A | N135: #N/A | P135: =IF(K135<>"",N135=D135,"") -> #N/A
A136: 1 | B136: LU0549545142 | C136: 100 | D136: Bloomberg Euro Aggregate (EUR) | E136: MS_RagSAA82 | F136: TF | G136: FALSE | K136: EMU0 Index | L136: EUR | M136: N | N136: ICE BofAML Euro Broad Market | P136: =IF(K136<>"",N136=D136,"") -> FALSE
A137: 45809 | B137: LU0549545142 | C137: 100 | D137: ICE BofAML Euro Broad Market | E137: MS_RagSAA82 | F137: TF | G137: FALSE | H137: ICE | I137: EMU0 Index | J137: Changed due to License | K137: EMU0 Index | L137: EUR | M137: N | N137: ICE BofAML Euro Broad Market | P137: =IF(K137<>"",N137=D137,"") -> TRUE
A138: 1 | B138: LU0626261944 | C138: 100 | D138: MSCI World Information Technology | E138: MS_RagSAA33 | F138: TF | G138: FALSE | K138: MXWO0IT Index | L138: USD | M138: N | N138: MSCI World Information Technology | P138: =IF(K138<>"",N138=D138,"") -> TRUE
A139: 1 | B139: LU0629658435 | C139: 75 | D139: BLOOMBERG EM USD AGG HY | E139: MS_RagSAA91 | F139: TF | G139: TRUE | K139: ID00 Index | L139: USD | M139: N | N139: ICE US EM Sovereign & Credit | P139: =IF(K139<>"",N139=D139,"") -> FALSE
A140: 1 | B140: LU0629658435 | C140: 25 | D140: BLOOMBERG EM USD IG | E140: MS_RagSAA91 | F140: TF | G140: TRUE | K140: ID00 Index | L140: USD | M140: N | N140: ICE US EM Sovereign & Credit | P140: =IF(K140<>"",N140=D140,"") -> FALSE
A141: 45809 | B141: LU0629658435 | C141: 55 | D141: ICE BofAML High Yield US Emerging Markets Liquid Corporate Plus Constrained | E141: MS_RagSAA91 | F141: TF | G141: TRUE | H141: ICE | I141: ECHY Index | J141: Changed due to License | K141: ID00 Index | L141: USD | M141: N | N141: ICE US EM Sovereign & Credit | P141: =IF(K141<>"",N141=D141,"") -> FALSE
A142: 45809 | B142: LU0629658435 | C142: 45 | D142: ICE BofAML US Emerging Markets External Sovereign | E142: MS_RagSAA91 | F142: TF | G142: TRUE | H142: ICE | I142: DGOV Index | J142: Changed due to License | K142: ID00 Index | L142: USD | M142: N | N142: ICE US EM Sovereign & Credit | P142: =IF(K142<>"",N142=D142,"") -> FALSE
A143: 1 | B143: LU0840615578 | C143: 100 | D143: MSCI Germany IMI | E143: MS_RagSAA5 | F143: TF | G143: FALSE | K143: MXDE Index | L143: EUR | M143: N | N143: MSCI Germany | P143: =IF(K143<>"",N143=D143,"") -> FALSE
A144: 1 | B144: LU0853555893 | C144: 70 | D144: ICE Global Broad Markets EUR Unhedged (GBMI) | E144: MS_RagSAA89 | F144: TF | G144: TRUE | K144: GBMI Index | L144: EUR | M144: N | N144: ICE BofAML Global Broad Market | P144: =IF(K144<>"",N144=D144,"") -> FALSE
A145: 1 | B145: LU0853555893 | C145: 30 | D145: Global HY Constrained EUR Unhedged (HW0C) | E145: MS_RagSAA89 | F145: TF | G145: TRUE | K145: GBMI Index | L145: EUR | M145: N | N145: ICE BofAML Global Broad Market | P145: =IF(K145<>"",N145=D145,"") -> FALSE
A146: 1 | B146: LU0869500495 | C146: 100 | D146: MSCI India IMI | E146: MS_RagSAA45 | F146: TF | G146: FALSE | K146: MXINIM Index | L146: EUR | M146: N | N146: MSCI India IMI | P146: =IF(K146<>"",N146=D146,"") -> TRUE
A147: 1 | B147: LU1057489228 | C147: 100 | D147: MSCI AC Asia Pacific ex Japan | E147: MS_RagSAA48 | F147: TF | G147: FALSE | K147: M1APJ Index | L147: EUR | M147: N | N147: MSCI AC Asia Pacific ex-Japan | P147: =IF(K147<>"",N147=D147,"") -> FALSE
A148: 1 | B148: LU1235249262 | C148: 100 | D148: MSCI China All Shares | E148: MS_RagSAA47 | F148: TF | G148: FALSE | K148: MXCNANM Index | L148: USD | M148: N | N148: MSCI China All Shares | P148: =IF(K148<>"",N148=D148,"") -> TRUE
A149: 1 | B149: LU1493701376 | C149: 100 | D149: MSCI AC Asia Pacific Value | E149: MS_RagSAA57 | F149: TF | G149: FALSE | K149: MAAP Index | L149: EUR | M149: N | N149: MSCI AC Asia Pacific | P149: =IF(K149<>"",N149=D149,"") -> FALSE
A150: 1 | B150: LU1505937943 | C150: 100 | D150: MSCI Europe ex UK Growth | E150: MS_RagSAA19 | F150: TF | G150: FALSE | K150: MXEUG Index | L150: EUR | M150: N | N150: MSCI Europe Excluding United Kingdom | P150: =IF(K150<>"",N150=D150,"") -> FALSE
A151: 1 | B151: LU1616921232 | C151: 100 | D151: MSCI EMU | E151: MS_RagSAA23 | F151: TF | G151: FALSE | K151: #N/A | L151: #N/A | M151: #N/A | N151: #N/A | P151: =IF(K151<>"",N151=D151,"") -> #N/A
A152: 1 | B152: LU1727358514 | C152: 100 | D152: ICE US Broad Market USD Unhedged - (US00) | E152: MS_RagSAA88 | F152: TF | G152: FALSE | K152: US00 Index | L152: USD | M152: N | N152: ICE BofAML US Broad Market | P152: TRUE
A153: 1 | B153: LU1802245560 | C153: 50 | D153: MSCI EM IMI | E153: MS_RagSAA60 | F153: TF | G153: TRUE | K153: MXEF Index | L153: EUR | M153: N | N153: MSCI Emerging Markets | P153: =IF(K153<>"",N153=D153,"") -> FALSE
A154: 1 | B154: LU1802245560 | C154: 50 | D154: MSCI EM IMI Growth | E154: MS_RagSAA60 | F154: TF | G154: TRUE | K154: MXEF Index | L154: EUR | M154: N | N154: MSCI Emerging Markets | P154: =IF(K154<>"",N154=D154,"") -> FALSE
A155: 1 | B155: LU1870374508 | C155: 100 | D155: MSCI Japan IMI | E155: MS_RagSAA6 | F155: TF | G155: FALSE | K155: MXJP Index | L155: EUR | M155: N | N155: MSCI Japan Index | P155: =IF(K155<>"",N155=D155,"") -> FALSE
A156: 1 | B156: LU1920210579 | C156: 100 | D156: MSCI Europe | E156: MS_RagSAA25 | F156: TF | G156: FALSE | K156: MXEU Index | L156: EUR | M156: N | N156: MSCI Europe | P156: =IF(K156<>"",N156=D156,"") -> TRUE
A157: 1 | B157: LU1920216006 | C157: 100 | D157: MSCI Europe Small Cap | E157: MS_RagSAA26 | F157: TF | G157: FALSE | K157: #N/A | L157: #N/A | M157: #N/A | N157: #N/A | P157: =IF(K157<>"",N157=D157,"") -> #N/A
A158: 1 | B158: LU1965304444 | C158: 100 | D158: MSCI Europe | E158: MS_RagSAA27 | F158: TF | G158: FALSE | K158: MXEU Index | L158: EUR | M158: N | N158: MSCI Europe | P158: =IF(K158<>"",N158=D158,"") -> TRUE
A159: 1 | B159: LU1968468162 | C159: 100 | D159: MSCI Germany IMI | E159: MS_RagSAA28 | F159: TF | G159: FALSE | K159: MXDE Index | L159: EUR | M159: N | N159: MSCI Germany | P159: =IF(K159<>"",N159=D159,"") -> FALSE
A160: 1 | B160: LU2041044764 | C160: 100 | D160: MSCI World | E160: MS_RagSAA18 | F160: TF | G160: FALSE | K160: MXWD Index | L160: EUR | M160: N | N160: MSCI AC World | P160: =IF(K160<>"",N160=D160,"") -> FALSE
A161: 1 | B161: LU2200556392 | C161: 50 | D161: MSCI China All Shares | E161: MS_RagSAA17 | F161: TF | G161: TRUE | K161: MXCNANM Index | L161: USD | M161: N | N161: MSCI China All Shares | P161: =IF(K161<>"",N161=D161,"") -> TRUE
A162: 1 | B162: LU2200556392 | C162: 50 | D162: MSCI China All Shares Quality | E162: MS_RagSAA17 | F162: TF | G162: TRUE | K162: MXCNANM Index | L162: USD | M162: N | N162: MSCI China All Shares | P162: =IF(K162<>"",N162=D162,"") -> FALSE
A163: 1 | B163: LU2444715366 | C163: 100 | D163: MSCI India IMI | E163: MS_RagSAA1 | F163: TF | G163: FALSE | K163: MXINIM Index | L163: USD | M163: N | N163: MSCI India IMI | P163: =IF(K163<>"",N163=D163,"") -> TRUE

Sheet Sheet1
A1: Strategy_Name | B1: Asset_Class | C1: Currency | D1: Managed_Account_ID
A2: DWS German Equity | B2: Equity | C2: EUR | D2: MA10
A3: Wellington Global Consumer | B3: Equity | C3: EUR | D3: MA100
A4: Acadian European Equity | B4: Equity | C4: EUR | D4: MA105
A5: GS All China Equity | B5: Equity | C5: EUR | D5: MA109
A6: MSIM Short Duration Global Bond (CH Int Income) | B6: Fixed Income | C6: EUR | D6: MA11
A7: KBI Circular Economy | B7: Equity | C7: EUR | D7: MA111
A8: Pictet Circular Economy | B8: Equity | C8: EUR | D8: MA112
A9: Eleva European Select Equity Large-Cap | B9: Equity | C9: EUR | D9: MA117
A10: MSIM Global Bond (CH Int Bond) | B10: Fixed Income | C10: EUR | D10: MA12
A11: BlueBay Global IG Credit | B11: Fixed Income | C11: EUR | D11: MA124
A12: Capital Four EUR High Yield | B12: Fixed Income | C12: EUR | D12: MA125
... A80: Zazove Global Convertible | B80: Fixed Income | C80: USD | D80: MA618

Sheet Exceptions
A1: Change Date | B1: ID_Code | C1: Weight | D1: SAA | E1: PreMerge_BlendID | F1: Type | G1: IsComposite | H1: Source | I1: Ticker | J1: Hedged | K1: Currency | L1: Comment
A2: 1 | B2: IE00027GCDQ6 | C2: 0.7 | D2: ICE BB-B Global High Yield - HW40 | E2: MS_RagSAA101 | F2: TF | G2: TRUE | H2: ICE | I2: HW40 Index | J2: FALSE | K2: USD
A3: 1 | B3: IE00027GCDQ6 | C3: 0.3 | D3: ICE BBB Global Corporate - GBC4 | E3: MS_RagSAA101 | F3: TF | G3: TRUE | H3: ICE | I3: GBC4 Index | J3: FALSE | K3: USD
A4: 1 | B4: LU0399027886 | C4: 0.8 | D4: ICE Global Broad Markets EUR Hedged (GBMI) | E4: MS_RagSAA87 | F4: TF | G4: TRUE | H4: ICE | I4: GBMI Index | J4: FALSE | K4: EUR
A5: 1 | B5: LU0399027886 | C5: 0.2 | D5: ICE Global HY Constrained EUR Hedged (HW0C) | E5: MS_RagSAA87 | F5: TF | G5: TRUE | H5: ICE | I5: HW0C Index | J5: FALSE | K5: EUR
A6: 45809 | B6: LU0629658435 | C6: 0.55 | D6: ICE BofAML High Yield US Emerging Markets Liquid Corporate Plus Constrained | E6: MS_RagSAA91 | F6: TF | G6: TRUE | H6: ICE | I6: ECHY Index | J6: FALSE | K6: USD | L6: Changed due to License
A7: 45809 | B7: LU0629658435 | C7: 0.45 | D7: ICE BofAML US Emerging Markets External Sovereign | E7: MS_RagSAA91 | F7: TF | G7: TRUE | H7: ICE | I7: DGOV Index | J7: FALSE | K7: USD | L7: Changed due to License
A8: 1 | B8: LU0853555893 | C8: 0.7 | D8: ICE Global Broad Markets EUR Unhedged (GBMI) | E8: MS_RagSAA89 | F8: TF | G8: TRUE | H8: ICE | I8: GBMI Index | J8: FALSE | K8: EUR
A9: 1 | B9: LU0853555893 | C9: 0.3 | D9: Global HY Constrained EUR Unhedged (HW0C) | E9: MS_RagSAA89 | F9: TF | G9: TRUE | H9: ICE | I9: HW0C Index | J9: FALSE | K9: EUR
A10: 1 | B10: LU1802245560 | C10: 0.5 | D10: MSCI EM IMI | E10: MS_RagSAA60 | F10: TF | G10: TRUE | H10: MSCI | I10: MIMUEMRN Index | J10: FALSE | K10: EUR
A11: 1 | B11: LU1802245560 | C11: 0.5 | D11: MSCI EM IMI Growth | E11: MS_RagSAA60 | F11: TF | G11: TRUE | H11: MSCI | I11: M1EF0008 Index | J11: FALSE | K11: EUR
A12: 1 | B12: LU2200556392 | C12: 0.5 | D12: MSCI China All Shares | E12: MS_RagSAA17 | F12: TF | G12: TRUE | H12: MSCI | I12: MXCNANM Index | J12: FALSE | K12: EUR
A13: 1 | B13: LU2200556392 | C13: 0.5 | D13: MSCI China All Shares Quality | E13: MS_RagSAA17 | F13: TF | G13: TRUE | H13: MSCI | J13: FALSE | K13: EUR
A14: 1 | B14: IE0007LWGYY1 | C14: 0.5 | D14: ICE BofA US Emerging Markets External Sovereign | E14: MS_RagSAA78 | F14: TF | G14: TRUE | H14: ICE | I14: DGOV Index | J14: FALSE | K14: EUR
A15: 1 | B15: IE0007LWGYY1 | C15: 0.5 | D15: ICE BofA Diversified Emerging Markets Sovereign Bond | E15: MS_RagSAA78 | F15: TF | G15: TRUE | H15: ICE | I15: WALD Index | J15: FALSE | K15: EUR
A16: 1 | B16: IE00BKTZQN06 | C16: 1 | D16: MSCI World Core Infrastructure | F16: TF | G16: FALSE | H16: MSCI | I16: M8CXRARA Index | J16: FALSE | K16: EUR | L16: license issues in FS
A17: 1 | B17: IE00BFY85J84 | C17: 1 | D17: MSCI World Core Infrastructure | F17: TF | G17: FALSE | H17: MSCI | I17: M8CXRARA Index | J17: FALSE | K17: EUR | L17: license issues in FS
A18: 1 | B18: IE00BNHQBY28 | C18: 1 | D18: MSCI World Core Infrastructure | F18: TF | G18: FALSE | H18: MSCI | I18: M8CXRARA Index | J18: FALSE | K18: EUR | L18: license issues in FS
